{
  "Aatrox_top": {
    "runes": [
      "8010",
      "9111",
      "9105",
      "8299",
      "8473",
      "8453"
    ],
    "items": [
      "3161",
      "6699",
      "6694"
    ],
    "starters": [
      "1054",
      "2003",
      "1055"
    ],
    "boots": "3047",
    "fetchedAt": "2026-04-20T01:50:39.154Z"
  },
  "Aatrox_jg": {
    "runes": [
      "8010",
      "9111",
      "9105",
      "8299",
      "8473",
      "8453"
    ],
    "items": [
      "3161",
      "6699",
      "6694"
    ],
    "starters": [
      "1054",
      "2003",
      "1055"
    ],
    "boots": "3047",
    "fetchedAt": "2026-04-20T01:50:41.247Z"
  },
  "Ahri_mid": {
    "runes": [
      "8112",
      "8139",
      "8140",
      "8106",
      "8226",
      "8210"
    ],
    "items": [
      "3118",
      "4645",
      "3157"
    ],
    "starters": [
      "1056",
      "2003",
      "1082",
      "2031"
    ],
    "boots": "3020",
    "fetchedAt": "2026-04-20T01:50:44.314Z"
  },
  "Akali_mid": {
    "runes": [
      "8112",
      "8143",
      "8140",
      "8106",
      "8444",
      "8451"
    ],
    "items": [
      "3146",
      "4645",
      "3157"
    ],
    "starters": [
      "1056",
      "2003",
      "1054"
    ],
    "boots": "3020",
    "fetchedAt": "2026-04-20T01:50:46.372Z"
  },
  "Akali_top": {
    "runes": [
      "8112",
      "8143",
      "8140",
      "8106",
      "8444",
      "8451"
    ],
    "items": [
      "3146",
      "4645",
      "3157"
    ],
    "starters": [
      "1056",
      "2003",
      "1054"
    ],
    "boots": "3020",
    "fetchedAt": "2026-04-20T01:50:48.423Z"
  },
  "Alistar_sup": {
    "runes": [
      "8439",
      "8463",
      "8473",
      "8242",
      "8306",
      "8347"
    ],
    "items": [
      "3190",
      "3050",
      "3109"
    ],
    "starters": [
      "2003"
    ],
    "boots": "3009",
    "fetchedAt": "2026-04-20T01:50:50.446Z"
  },
  "Amumu_jg": {
    "runes": [
      "8010",
      "9111",
      "9105",
      "8299",
      "8126",
      "8106"
    ],
    "items": [
      "6653",
      "3068",
      "8020"
    ],
    "starters": [
      "1103",
      "2003"
    ],
    "boots": "3047",
    "fetchedAt": "2026-04-20T01:50:52.464Z"
  },
  "Amumu_sup": {
    "runes": [
      "8010",
      "9111",
      "9105",
      "8299",
      "8126",
      "8106"
    ],
    "items": [
      "6653",
      "3068",
      "8020"
    ],
    "starters": [
      "1103",
      "2003"
    ],
    "boots": "3047",
    "fetchedAt": "2026-04-20T01:50:54.515Z"
  },
  "Annie_mid": {
    "runes": [
      "8112",
      "8126",
      "8140",
      "8105",
      "8224",
      "8233"
    ],
    "items": [
      "3118",
      "4646",
      "4645"
    ],
    "starters": [
      "1056",
      "2003",
      "1052"
    ],
    "boots": "3020",
    "fetchedAt": "2026-04-20T01:50:56.587Z"
  },
  "Annie_sup": {
    "runes": [
      "8112",
      "8126",
      "8140",
      "8105",
      "8224",
      "8233"
    ],
    "items": [
      "3118",
      "4646",
      "4645"
    ],
    "starters": [
      "1056",
      "2003",
      "1052"
    ],
    "boots": "3020",
    "fetchedAt": "2026-04-20T01:50:58.610Z"
  },
  "Ashe_adc": {
    "runes": [
      "8008",
      "8009",
      "9104",
      "8017",
      "8345",
      "8410"
    ],
    "items": [
      "6672",
      "3046",
      "3031"
    ],
    "starters": [
      "1055",
      "2003"
    ],
    "boots": "3006",
    "fetchedAt": "2026-04-20T01:51:01.169Z"
  },
  "Ashe_sup": {
    "runes": [
      "8008",
      "8009",
      "9104",
      "8017",
      "8345",
      "8410"
    ],
    "items": [
      "6672",
      "3046",
      "3031"
    ],
    "starters": [
      "1055",
      "2003"
    ],
    "boots": "3006",
    "fetchedAt": "2026-04-20T01:51:03.138Z"
  },
  "Bard_sup": {
    "runes": [
      "8112",
      "8126",
      "8141",
      "8135",
      "8304",
      "8316"
    ],
    "items": [
      "3742",
      "2524",
      "3190"
    ],
    "starters": [
      "2003"
    ],
    "boots": "3009",
    "fetchedAt": "2026-04-20T01:51:05.135Z"
  },
  "Blitzcrank_sup": {
    "runes": [
      "8351",
      "8306",
      "8345",
      "8347",
      "8275",
      "8234"
    ],
    "items": [
      "3190",
      "3050",
      "2524"
    ],
    "starters": [
      "2003"
    ],
    "boots": "3009",
    "fetchedAt": "2026-04-20T01:51:07.387Z"
  },
  "Brand_sup": {
    "runes": [
      "8229",
      "8226",
      "8210",
      "8237",
      "8345",
      "8347"
    ],
    "items": [
      "3116",
      "6653",
      "3165"
    ],
    "starters": [
      "2003"
    ],
    "boots": "3020",
    "fetchedAt": "2026-04-20T01:51:09.440Z"
  },
  "Brand_mid": {
    "runes": [
      "8229",
      "8226",
      "8210",
      "8237",
      "8345",
      "8347"
    ],
    "items": [
      "3116",
      "6653",
      "3165"
    ],
    "starters": [
      "2003"
    ],
    "boots": "3020",
    "fetchedAt": "2026-04-20T01:51:11.586Z"
  },
  "Brand_jg": {
    "runes": [
      "8229",
      "8226",
      "8210",
      "8237",
      "8345",
      "8347"
    ],
    "items": [
      "3116",
      "6653",
      "3165"
    ],
    "starters": [
      "2003"
    ],
    "boots": "3020",
    "fetchedAt": "2026-04-20T01:51:13.743Z"
  },
  "Brand_adc": {
    "runes": [
      "8229",
      "8226",
      "8210",
      "8237",
      "8345",
      "8347"
    ],
    "items": [
      "3116",
      "6653",
      "3165"
    ],
    "starters": [
      "2003"
    ],
    "boots": "3020",
    "fetchedAt": "2026-04-20T01:51:15.732Z"
  },
  "Braum_sup": {
    "runes": [
      "8465",
      "8463",
      "8473",
      "8242",
      "8345",
      "8347"
    ],
    "items": [
      "2524",
      "3190",
      "3109"
    ],
    "starters": [
      "2003"
    ],
    "boots": "3047",
    "fetchedAt": "2026-04-20T01:51:17.709Z"
  },
  "Caitlyn_adc": {
    "runes": [
      "8008",
      "8009",
      "9103",
      "8014",
      "8233",
      "8236"
    ],
    "items": [
      "2523",
      "3031",
      "3094"
    ],
    "starters": [
      "1055",
      "2003",
      "1083"
    ],
    "boots": "3006",
    "fetchedAt": "2026-04-20T01:51:19.652Z"
  },
  "Camille_top": {
    "runes": [
      "8437",
      "8401",
      "8473",
      "8242",
      "8304",
      "8345"
    ],
    "items": [
      "3078",
      "3074",
      "6333"
    ],
    "starters": [
      "1055",
      "2003",
      "1054"
    ],
    "boots": "3047",
    "fetchedAt": "2026-04-20T01:51:22.515Z"
  },
  "Camille_jg": {
    "runes": [
      "8437",
      "8401",
      "8473",
      "8242",
      "8304",
      "8345"
    ],
    "items": [
      "3078",
      "3074",
      "6333"
    ],
    "starters": [
      "1055",
      "2003",
      "1054"
    ],
    "boots": "3047",
    "fetchedAt": "2026-04-20T01:51:24.508Z"
  },
  "Darius_top": {
    "runes": [
      "8010",
      "9111",
      "9104",
      "8299",
      "8224",
      "8234"
    ],
    "items": [
      "3142",
      "3742",
      "6333"
    ],
    "starters": [
      "1055",
      "2003",
      "1054"
    ],
    "boots": "3047",
    "fetchedAt": "2026-04-20T01:51:26.472Z"
  },
  "Darius_jg": {
    "runes": [
      "8010",
      "9111",
      "9104",
      "8299",
      "8224",
      "8234"
    ],
    "items": [
      "3142",
      "3742",
      "6333"
    ],
    "starters": [
      "1055",
      "2003",
      "1054"
    ],
    "boots": "3047",
    "fetchedAt": "2026-04-20T01:51:28.958Z"
  },
  "Diana_jg": {
    "runes": [
      "8112",
      "8143",
      "8140",
      "8135",
      "8401",
      "8473"
    ],
    "items": [
      "4646",
      "4645",
      "3157"
    ],
    "starters": [
      "1056",
      "2003",
      "1082",
      "2031"
    ],
    "boots": "3020",
    "fetchedAt": "2026-04-20T01:51:31.081Z"
  },
  "Diana_mid": {
    "runes": [
      "8112",
      "8143",
      "8140",
      "8135",
      "8401",
      "8473"
    ],
    "items": [
      "4646",
      "4645",
      "3157"
    ],
    "starters": [
      "1056",
      "2003",
      "1082",
      "2031"
    ],
    "boots": "3020",
    "fetchedAt": "2026-04-20T01:51:33.157Z"
  },
  "Draven_adc": {
    "runes": [
      "8008",
      "8009",
      "9104",
      "8017",
      "8321",
      "8313"
    ],
    "items": [
      "6697",
      "2523",
      "3031"
    ],
    "starters": [
      "1055",
      "2003",
      "1036"
    ],
    "boots": "3006",
    "fetchedAt": "2026-04-20T01:51:35.159Z"
  },
  "Ezreal_adc": {
    "runes": [
      "8008",
      "8009",
      "9103",
      "8014",
      "8304",
      "8345"
    ],
    "items": [
      "3078",
      "3042",
      "2517"
    ],
    "starters": [
      "1055",
      "2003",
      "3070"
    ],
    "boots": "3047",
    "fetchedAt": "2026-04-20T01:51:39.234Z"
  },
  "Fiora_top": {
    "runes": [
      "8005",
      "9111",
      "9104",
      "8299",
      "8345",
      "8316"
    ],
    "items": [
      "3074",
      "3078",
      "6333"
    ],
    "starters": [
      "1055",
      "2003",
      "1054"
    ],
    "boots": "3047",
    "fetchedAt": "2026-04-20T01:51:41.205Z"
  },
  "Fizz_mid": {
    "runes": [
      "8112",
      "8143",
      "8140",
      "8135",
      "8210",
      "8237"
    ],
    "items": [
      "3100",
      "3157",
      "3089"
    ],
    "starters": [
      "1056",
      "2003",
      "1082"
    ],
    "boots": "3020",
    "fetchedAt": "2026-04-20T01:51:43.159Z"
  },
  "Fizz_jg": {
    "runes": [
      "8112",
      "8143",
      "8140",
      "8135",
      "8210",
      "8237"
    ],
    "items": [
      "3100",
      "3157",
      "3089"
    ],
    "starters": [
      "1056",
      "2003",
      "1082"
    ],
    "boots": "3020",
    "fetchedAt": "2026-04-20T01:51:45.254Z"
  },
  "Garen_top": {
    "runes": [
      "8010",
      "9111",
      "9105",
      "8299",
      "8224",
      "8234"
    ],
    "items": [
      "6631",
      "3046",
      "3033"
    ],
    "starters": [
      "1054",
      "2003",
      "1055"
    ],
    "boots": "3006",
    "fetchedAt": "2026-04-20T01:51:47.222Z"
  },
  "Graves_jg": {
    "runes": [
      "8128",
      "8143",
      "8140",
      "8135",
      "9111",
      "9104"
    ],
    "items": [
      "6697",
      "6676",
      "3036"
    ],
    "starters": [
      "1101",
      "2003"
    ],
    "boots": "3047",
    "fetchedAt": "2026-04-20T01:51:49.162Z"
  },
  "Hecarim_jg": {
    "runes": [
      "8230",
      "8275",
      "8234",
      "8232",
      "9111",
      "9105"
    ],
    "items": [
      "3161",
      "3071",
      "6333"
    ],
    "starters": [
      "1102",
      "2003"
    ],
    "boots": "3111",
    "fetchedAt": "2026-04-20T01:51:51.128Z"
  },
  "Irelia_top": {
    "runes": [
      "8010",
      "9111",
      "9104",
      "8299",
      "8313",
      "8316"
    ],
    "items": [
      "3153",
      "3181",
      "3091"
    ],
    "starters": [
      "1055",
      "2003",
      "1054"
    ],
    "boots": "3047",
    "fetchedAt": "2026-04-20T01:51:53.102Z"
  },
  "Irelia_mid": {
    "runes": [
      "8010",
      "9111",
      "9104",
      "8299",
      "8313",
      "8316"
    ],
    "items": [
      "3153",
      "3181",
      "3091"
    ],
    "starters": [
      "1055",
      "2003",
      "1054"
    ],
    "boots": "3047",
    "fetchedAt": "2026-04-20T01:51:55.030Z"
  },
  "Janna_sup": {
    "runes": [
      "8214",
      "8226",
      "8234",
      "8236",
      "8463",
      "8453"
    ],
    "items": [
      "6617",
      "3107",
      "2065"
    ],
    "starters": [
      "2003"
    ],
    "boots": "3009",
    "fetchedAt": "2026-04-20T01:51:57.193Z"
  },
  "JarvanIV_jg": {
    "runes": [
      "8010",
      "9111",
      "9104",
      "8014",
      "8304",
      "8347"
    ],
    "items": [
      "6610",
      "3071",
      "3026"
    ],
    "starters": [
      "1101",
      "2003"
    ],
    "boots": "3047",
    "fetchedAt": "2026-04-20T01:51:59.148Z"
  },
  "Jax_top": {
    "runes": [
      "8008",
      "9111",
      "9104",
      "8299",
      "8473",
      "8242"
    ],
    "items": [
      "3078",
      "6610",
      "3157"
    ],
    "starters": [
      "1055",
      "2003",
      "1054"
    ],
    "boots": "3047",
    "fetchedAt": "2026-04-20T01:52:01.272Z"
  },
  "Jax_jg": {
    "runes": [
      "8008",
      "9111",
      "9104",
      "8299",
      "8473",
      "8242"
    ],
    "items": [
      "3078",
      "6610",
      "3157"
    ],
    "starters": [
      "1055",
      "2003",
      "1054"
    ],
    "boots": "3047",
    "fetchedAt": "2026-04-20T01:52:03.356Z"
  },
  "Jayce_top": {
    "runes": [
      "8010",
      "8009",
      "9104",
      "8299",
      "8304",
      "8345"
    ],
    "items": [
      "3142",
      "3042",
      "6694"
    ],
    "starters": [
      "1055",
      "2003",
      "1054"
    ],
    "boots": "3047",
    "fetchedAt": "2026-04-20T01:52:06.215Z"
  },
  "Jayce_mid": {
    "runes": [
      "8010",
      "8009",
      "9104",
      "8299",
      "8304",
      "8345"
    ],
    "items": [
      "3142",
      "3042",
      "6694"
    ],
    "starters": [
      "1055",
      "2003",
      "1054"
    ],
    "boots": "3047",
    "fetchedAt": "2026-04-20T01:52:08.266Z"
  },
  "Jinx_adc": {
    "runes": [
      "8008",
      "8009",
      "9103",
      "8017",
      "8321",
      "8313"
    ],
    "items": [
      "2523",
      "3046",
      "3031"
    ],
    "starters": [
      "1055",
      "2003",
      "1083"
    ],
    "boots": "3006",
    "fetchedAt": "2026-04-20T01:52:10.295Z"
  },
  "Kaisa_adc": {
    "runes": [
      "8008",
      "8009",
      "9103",
      "8014",
      "8304",
      "8345"
    ],
    "items": [
      "6672",
      "3124",
      "2510"
    ],
    "starters": [
      "1055",
      "2003",
      "1036"
    ],
    "boots": "3006",
    "fetchedAt": "2026-04-20T01:52:12.412Z"
  },
  "Kalista_adc": {
    "runes": [
      "8008",
      "9111",
      "9104",
      "8299",
      "8143",
      "8135"
    ],
    "items": [
      "3153",
      "3124",
      "3302"
    ],
    "starters": [
      "1055",
      "2003",
      "3599"
    ],
    "boots": "3006",
    "fetchedAt": "2026-04-20T01:52:14.540Z"
  },
  "Karma_sup": {
    "runes": [
      "8214",
      "8226",
      "8210",
      "8236",
      "8463",
      "8453"
    ],
    "items": [
      "6620",
      "6617",
      "3107"
    ],
    "starters": [
      "2003"
    ],
    "boots": "3009",
    "fetchedAt": "2026-04-20T01:52:16.491Z"
  },
  "Karma_mid": {
    "runes": [
      "8214",
      "8226",
      "8210",
      "8236",
      "8463",
      "8453"
    ],
    "items": [
      "6620",
      "6617",
      "3107"
    ],
    "starters": [
      "2003"
    ],
    "boots": "3009",
    "fetchedAt": "2026-04-20T01:52:19.265Z"
  },
  "Katarina_mid": {
    "runes": [
      "8112",
      "8143",
      "8140",
      "8105",
      "9111",
      "8014"
    ],
    "items": [
      "6672",
      "3153",
      "3302"
    ],
    "starters": [
      "1082",
      "2031",
      "1055",
      "2003"
    ],
    "boots": "3020",
    "fetchedAt": "2026-04-20T01:52:21.244Z"
  },
  "Khazix_jg": {
    "runes": [
      "8369",
      "8321",
      "8313",
      "8347",
      "8143",
      "8135"
    ],
    "items": [
      "3179",
      "2520",
      "3814"
    ],
    "starters": [
      "1102",
      "2003"
    ],
    "boots": "3111",
    "fetchedAt": "2026-04-20T01:52:23.188Z"
  },
  "Kindred_jg": {
    "runes": [
      "8005",
      "9111",
      "9104",
      "8014",
      "8143",
      "8135"
    ],
    "items": [
      "6672",
      "6676",
      "3036"
    ],
    "starters": [
      "1101",
      "2003"
    ],
    "boots": "3006",
    "fetchedAt": "2026-04-20T01:52:25.205Z"
  },
  "Kled_top": {
    "runes": [
      "8010",
      "9111",
      "9104",
      "8299",
      "8446",
      "8473"
    ],
    "items": [
      "3748",
      "3181",
      "2501"
    ],
    "starters": [
      "1055",
      "2003",
      "1054"
    ],
    "boots": "3047",
    "fetchedAt": "2026-04-20T01:52:27.127Z"
  },
  "LeeSin_jg": {
    "runes": [
      "8010",
      "9111",
      "9104",
      "8014",
      "8304",
      "8347"
    ],
    "items": [
      "6692",
      "6610",
      "6333"
    ],
    "starters": [
      "1101",
      "2003"
    ],
    "boots": "3047",
    "fetchedAt": "2026-04-20T01:52:29.250Z"
  },
  "Leona_sup": {
    "runes": [
      "8439",
      "8463",
      "8473",
      "8242",
      "8345",
      "8347"
    ],
    "items": [
      "3190",
      "2524",
      "3109"
    ],
    "starters": [
      "2003"
    ],
    "boots": "3047",
    "fetchedAt": "2026-04-20T01:52:31.838Z"
  },
  "Lucian_adc": {
    "runes": [
      "8005",
      "8009",
      "9103",
      "8014",
      "8304",
      "8345"
    ],
    "items": [
      "3508",
      "6675",
      "3031"
    ],
    "starters": [
      "1055",
      "2003",
      "1036"
    ],
    "boots": "3047",
    "fetchedAt": "2026-04-20T01:52:33.923Z"
  },
  "Lucian_mid": {
    "runes": [
      "8005",
      "8009",
      "9103",
      "8014",
      "8304",
      "8345"
    ],
    "items": [
      "3508",
      "6675",
      "3031"
    ],
    "starters": [
      "1055",
      "2003",
      "1036"
    ],
    "boots": "3047",
    "fetchedAt": "2026-04-20T01:52:35.858Z"
  },
  "Lulu_sup": {
    "runes": [
      "8214",
      "8226",
      "8210",
      "8237",
      "8473",
      "8453"
    ],
    "items": [
      "3504",
      "6617",
      "3107"
    ],
    "starters": [
      "2003"
    ],
    "boots": "3009",
    "fetchedAt": "2026-04-20T01:52:38.006Z"
  },
  "Lux_mid": {
    "runes": [
      "8229",
      "8226",
      "8210",
      "8237",
      "8126",
      "8106"
    ],
    "items": [
      "6655",
      "4646",
      "4645"
    ],
    "starters": [
      "2003"
    ],
    "boots": "3020",
    "fetchedAt": "2026-04-20T01:52:40.020Z"
  },
  "Lux_sup": {
    "runes": [
      "8229",
      "8226",
      "8210",
      "8237",
      "8126",
      "8106"
    ],
    "items": [
      "6655",
      "4646",
      "4645"
    ],
    "starters": [
      "2003"
    ],
    "boots": "3020",
    "fetchedAt": "2026-04-20T01:52:42.167Z"
  },
  "Malphite_top": {
    "runes": [
      "8229",
      "8226",
      "8210",
      "8237",
      "8444",
      "8451"
    ],
    "items": [
      "3068",
      "3075",
      "3110"
    ],
    "starters": [
      "1056",
      "2003",
      "1054"
    ],
    "boots": "3047",
    "fetchedAt": "2026-04-20T01:52:44.093Z"
  },
  "Malphite_sup": {
    "runes": [
      "8229",
      "8226",
      "8210",
      "8237",
      "8444",
      "8451"
    ],
    "items": [
      "3068",
      "3075",
      "3110"
    ],
    "starters": [
      "1056",
      "2003",
      "1054"
    ],
    "boots": "3047",
    "fetchedAt": "2026-04-20T01:52:47.243Z"
  },
  "Malphite_mid": {
    "runes": [
      "8229",
      "8226",
      "8210",
      "8237",
      "8444",
      "8451"
    ],
    "items": [
      "3068",
      "3075",
      "3110"
    ],
    "starters": [
      "1056",
      "2003",
      "1054"
    ],
    "boots": "3047",
    "fetchedAt": "2026-04-20T01:52:49.242Z"
  },
  "MasterYi_jg": {
    "runes": [
      "8008",
      "9111",
      "9104",
      "8014",
      "8304",
      "8347"
    ],
    "items": [
      "6672",
      "3124",
      "3073"
    ],
    "starters": [
      "1102",
      "2003"
    ],
    "boots": "3006",
    "fetchedAt": "2026-04-20T01:52:51.181Z"
  },
  "MissFortune_adc": {
    "runes": [
      "8369",
      "8321",
      "8345",
      "8316",
      "8226",
      "8236"
    ],
    "items": [
      "6697",
      "6676",
      "3031"
    ],
    "starters": [
      "1055",
      "2003",
      "1083"
    ],
    "boots": "3006",
    "fetchedAt": "2026-04-20T01:52:53.600Z"
  },
  "Morgana_sup": {
    "runes": [
      "8229",
      "8226",
      "8210",
      "8237",
      "8126",
      "8106"
    ],
    "items": [
      "6653",
      "3157",
      "3116"
    ],
    "starters": [
      "2003"
    ],
    "boots": "3020",
    "fetchedAt": "2026-04-20T01:52:55.579Z"
  },
  "Morgana_mid": {
    "runes": [
      "8229",
      "8226",
      "8210",
      "8237",
      "8126",
      "8106"
    ],
    "items": [
      "6653",
      "3157",
      "3116"
    ],
    "starters": [
      "2003"
    ],
    "boots": "3020",
    "fetchedAt": "2026-04-20T01:52:57.693Z"
  },
  "Nami_sup": {
    "runes": [
      "8214",
      "8226",
      "8210",
      "8237",
      "8473",
      "8453"
    ],
    "items": [
      "4005",
      "6617",
      "3504"
    ],
    "starters": [
      "2003"
    ],
    "boots": "3009",
    "fetchedAt": "2026-04-20T01:52:59.710Z"
  },
  "Nautilus_sup": {
    "runes": [
      "8439",
      "8401",
      "8473",
      "8242",
      "8345",
      "8347"
    ],
    "items": [
      "3190",
      "2524",
      "3109"
    ],
    "starters": [
      "2003"
    ],
    "boots": "3047",
    "fetchedAt": "2026-04-20T01:53:01.872Z"
  },
  "Nautilus_jg": {
    "runes": [
      "8439",
      "8401",
      "8473",
      "8242",
      "8345",
      "8347"
    ],
    "items": [
      "3190",
      "2524",
      "3109"
    ],
    "starters": [
      "2003"
    ],
    "boots": "3047",
    "fetchedAt": "2026-04-20T01:53:03.828Z"
  },
  "Nidalee_jg": {
    "runes": [
      "8128",
      "8143",
      "8140",
      "8135",
      "8210",
      "8232"
    ],
    "items": [
      "3100",
      "4645",
      "3157"
    ],
    "starters": [
      "1101",
      "2003"
    ],
    "boots": "3020",
    "fetchedAt": "2026-04-20T01:53:05.789Z"
  },
  "Nocturne_jg": {
    "runes": [
      "8010",
      "9111",
      "9104",
      "8299",
      "8140",
      "8106"
    ],
    "items": [
      "3073",
      "6631",
      "3071"
    ],
    "starters": [
      "1101",
      "2003"
    ],
    "boots": "3047",
    "fetchedAt": "2026-04-20T01:53:08.088Z"
  },
  "Nunu_jg": {
    "runes": [
      "8230",
      "8275",
      "8234",
      "8232",
      "9111",
      "9105"
    ],
    "items": [
      "6653",
      "3110",
      "2504"
    ],
    "starters": [
      "1102",
      "2003"
    ],
    "boots": "3047",
    "fetchedAt": "2026-04-20T01:53:10.040Z"
  },
  "Olaf_jg": {
    "runes": [
      "8010",
      "9111",
      "9104",
      "8299",
      "8345",
      "8410"
    ],
    "items": [
      "6631",
      "3073",
      "6333"
    ],
    "starters": [
      "1055",
      "2003",
      "1054"
    ],
    "boots": "3009",
    "fetchedAt": "2026-04-20T01:53:12.035Z"
  },
  "Olaf_top": {
    "runes": [
      "8010",
      "9111",
      "9104",
      "8299",
      "8345",
      "8410"
    ],
    "items": [
      "6631",
      "3073",
      "6333"
    ],
    "starters": [
      "1055",
      "2003",
      "1054"
    ],
    "boots": "3009",
    "fetchedAt": "2026-04-20T01:53:14.753Z"
  },
  "Orianna_mid": {
    "runes": [
      "8214",
      "8226",
      "8210",
      "8237",
      "8009",
      "8014"
    ],
    "items": [
      "6655",
      "4645",
      "3089"
    ],
    "starters": [
      "1056",
      "2003",
      "3070"
    ],
    "boots": "3020",
    "fetchedAt": "2026-04-20T01:53:16.878Z"
  },
  "Pantheon_top": {
    "runes": [
      "8005",
      "9111",
      "9105",
      "8014",
      "8126",
      "8105"
    ],
    "items": [
      "3179",
      "6692",
      "3071"
    ],
    "starters": [
      "2003"
    ],
    "boots": "3047",
    "fetchedAt": "2026-04-20T01:53:18.852Z"
  },
  "Pantheon_mid": {
    "runes": [
      "8005",
      "9111",
      "9105",
      "8014",
      "8126",
      "8105"
    ],
    "items": [
      "3179",
      "6692",
      "3071"
    ],
    "starters": [
      "2003"
    ],
    "boots": "3047",
    "fetchedAt": "2026-04-20T01:53:21.075Z"
  },
  "Pantheon_sup": {
    "runes": [
      "8005",
      "9111",
      "9105",
      "8014",
      "8126",
      "8105"
    ],
    "items": [
      "3179",
      "6692",
      "3071"
    ],
    "starters": [
      "2003"
    ],
    "boots": "3047",
    "fetchedAt": "2026-04-20T01:53:23.042Z"
  },
  "Pyke_sup": {
    "runes": [
      "9923",
      "8126",
      "8137",
      "8106",
      "8473",
      "8242"
    ],
    "items": [
      "3179",
      "3142",
      "3814"
    ],
    "starters": [
      "2003"
    ],
    "boots": "3009",
    "fetchedAt": "2026-04-20T01:53:26.115Z"
  },
  "Qiyana_mid": {
    "runes": [
      "8112",
      "8143",
      "8140",
      "8135",
      "8009",
      "8299"
    ],
    "items": [
      "6697",
      "6698",
      "6694"
    ],
    "starters": [
      "1055",
      "2003",
      "1036",
      "2031"
    ],
    "boots": "3111",
    "fetchedAt": "2026-04-20T01:53:28.107Z"
  },
  "Quinn_top": {
    "runes": [
      "8112",
      "8143",
      "8140",
      "8135",
      "8233",
      "8236"
    ],
    "items": [
      "6698",
      "6676",
      "3036"
    ],
    "starters": [
      "1055",
      "2003",
      "1036",
      "2031"
    ],
    "boots": "3006",
    "fetchedAt": "2026-04-20T01:53:30.163Z"
  },
  "Rakan_sup": {
    "runes": [
      "8465",
      "8463",
      "8473",
      "8242",
      "8137",
      "8106"
    ],
    "items": [
      "3050",
      "3190",
      "2524"
    ],
    "starters": [
      "2003"
    ],
    "boots": "3111",
    "fetchedAt": "2026-04-20T01:53:32.762Z"
  },
  "Renekton_top": {
    "runes": [
      "8010",
      "9111",
      "9104",
      "8299",
      "8473",
      "8242"
    ],
    "items": [
      "6692",
      "3071",
      "3053"
    ],
    "starters": [
      "1055",
      "2003",
      "1054"
    ],
    "boots": "3047",
    "fetchedAt": "2026-04-20T01:53:36.750Z"
  },
  "Rengar_jg": {
    "runes": [
      "8369",
      "8321",
      "8313",
      "8347",
      "8143",
      "8106"
    ],
    "items": [
      "3179",
      "6698",
      "3036"
    ],
    "starters": [
      "1102",
      "2003"
    ],
    "boots": "3009",
    "fetchedAt": "2026-04-20T01:53:38.788Z"
  },
  "Riven_top": {
    "runes": [
      "8010",
      "9111",
      "9105",
      "8299",
      "8321",
      "8316"
    ],
    "items": [
      "6696",
      "6610",
      "6333"
    ],
    "starters": [
      "1055",
      "2003",
      "1054"
    ],
    "boots": "3047",
    "fetchedAt": "2026-04-20T01:53:40.708Z"
  },
  "Samira_adc": {
    "runes": [
      "8010",
      "9111",
      "9103",
      "8299",
      "8139",
      "8135"
    ],
    "items": [
      "6676",
      "3031",
      "3036"
    ],
    "starters": [
      "1055",
      "2003",
      "1036"
    ],
    "boots": "3047",
    "fetchedAt": "2026-04-20T01:53:42.691Z"
  },
  "Sejuani_jg": {
    "runes": [
      "8439",
      "8463",
      "8429",
      "8451",
      "9111",
      "9104"
    ],
    "items": [
      "3084",
      "2502",
      "3075"
    ],
    "starters": [
      "1103",
      "2003"
    ],
    "boots": "3047",
    "fetchedAt": "2026-04-20T01:53:44.811Z"
  },
  "Senna_sup": {
    "runes": [
      "8021",
      "8009",
      "9104",
      "8017",
      "8473",
      "8453"
    ],
    "items": [
      "3071",
      "3094",
      "3031"
    ],
    "starters": [
      "2003"
    ],
    "boots": "3006",
    "fetchedAt": "2026-04-20T01:53:46.746Z"
  },
  "Senna_adc": {
    "runes": [
      "8021",
      "8009",
      "9104",
      "8017",
      "8473",
      "8453"
    ],
    "items": [
      "3071",
      "3094",
      "3031"
    ],
    "starters": [
      "2003"
    ],
    "boots": "3006",
    "fetchedAt": "2026-04-20T01:53:48.764Z"
  },
  "Seraphine_sup": {
    "runes": [
      "8214",
      "8226",
      "8210",
      "8236",
      "8463",
      "8453"
    ],
    "items": [
      "6620",
      "2530",
      "6617"
    ],
    "starters": [
      "2003"
    ],
    "boots": "3020",
    "fetchedAt": "2026-04-20T01:53:50.698Z"
  },
  "Seraphine_mid": {
    "runes": [
      "8214",
      "8226",
      "8210",
      "8236",
      "8463",
      "8453"
    ],
    "items": [
      "6620",
      "2530",
      "6617"
    ],
    "starters": [
      "2003"
    ],
    "boots": "3020",
    "fetchedAt": "2026-04-20T01:53:52.656Z"
  },
  "Shaco_jg": {
    "runes": [
      "9923",
      "8143",
      "8140",
      "8105",
      "9104",
      "8014"
    ],
    "items": [
      "3142",
      "6676",
      "3031"
    ],
    "starters": [
      "1102",
      "2003"
    ],
    "boots": "3006",
    "fetchedAt": "2026-04-20T01:53:54.847Z"
  },
  "Shaco_sup": {
    "runes": [
      "9923",
      "8143",
      "8140",
      "8105",
      "9104",
      "8014"
    ],
    "items": [
      "3142",
      "6676",
      "3031"
    ],
    "starters": [
      "1102",
      "2003"
    ],
    "boots": "3006",
    "fetchedAt": "2026-04-20T01:53:56.895Z"
  },
  "Shen_top": {
    "runes": [
      "8437",
      "8401",
      "8444",
      "8451",
      "8345",
      "8410"
    ],
    "items": [
      "3748",
      "2510",
      "2524"
    ],
    "starters": [
      "1054",
      "2003",
      "1055"
    ],
    "boots": "3047",
    "fetchedAt": "2026-04-20T01:53:58.928Z"
  },
  "Shen_jg": {
    "runes": [
      "8437",
      "8401",
      "8444",
      "8451",
      "8345",
      "8410"
    ],
    "items": [
      "3748",
      "2510",
      "2524"
    ],
    "starters": [
      "1054",
      "2003",
      "1055"
    ],
    "boots": "3047",
    "fetchedAt": "2026-04-20T01:54:01.057Z"
  },
  "Sivir_adc": {
    "runes": [
      "8008",
      "8009",
      "9103",
      "8017",
      "8321",
      "8313"
    ],
    "items": [
      "3508",
      "6675",
      "3031"
    ],
    "starters": [
      "1055",
      "2003",
      "1083"
    ],
    "boots": "3006",
    "fetchedAt": "2026-04-20T01:54:03.101Z"
  },
  "Sona_sup": {
    "runes": [
      "8214",
      "8226",
      "8210",
      "8236",
      "8429",
      "8453"
    ],
    "items": [
      "6620",
      "2530",
      "6617"
    ],
    "starters": [
      "2003"
    ],
    "boots": "3009",
    "fetchedAt": "2026-04-20T01:54:05.097Z"
  },
  "Soraka_sup": {
    "runes": [
      "8214",
      "8226",
      "8210",
      "8237",
      "8473",
      "8453"
    ],
    "items": [
      "6617",
      "3107",
      "6621"
    ],
    "starters": [
      "2003"
    ],
    "boots": "3009",
    "fetchedAt": "2026-04-20T01:54:07.032Z"
  },
  "Syndra_mid": {
    "runes": [
      "8369",
      "8304",
      "8345",
      "8347",
      "8226",
      "8210"
    ],
    "items": [
      "6655",
      "4645",
      "3089"
    ],
    "starters": [
      "1056",
      "2003"
    ],
    "boots": "3020",
    "fetchedAt": "2026-04-20T01:54:09.037Z"
  },
  "TahmKench_sup": {
    "runes": [
      "8437",
      "8401",
      "8444",
      "8242",
      "9111",
      "9104"
    ],
    "items": [
      "3084",
      "3075",
      "3065"
    ],
    "starters": [
      "2003"
    ],
    "boots": "3047",
    "fetchedAt": "2026-04-20T01:54:11.151Z"
  },
  "TahmKench_top": {
    "runes": [
      "8437",
      "8401",
      "8444",
      "8242",
      "9111",
      "9104"
    ],
    "items": [
      "3084",
      "3075",
      "3065"
    ],
    "starters": [
      "2003"
    ],
    "boots": "3047",
    "fetchedAt": "2026-04-20T01:54:13.081Z"
  },
  "Talon_mid": {
    "runes": [
      "8010",
      "9111",
      "9104",
      "8299",
      "8304",
      "8347"
    ],
    "items": [
      "6697",
      "3179",
      "6696"
    ],
    "starters": [
      "1101",
      "1102",
      "2003"
    ],
    "boots": "3009",
    "fetchedAt": "2026-04-20T01:54:15.109Z"
  },
  "Talon_jg": {
    "runes": [
      "8010",
      "9111",
      "9104",
      "8299",
      "8304",
      "8347"
    ],
    "items": [
      "6697",
      "3179",
      "6696"
    ],
    "starters": [
      "1101",
      "1102",
      "2003"
    ],
    "boots": "3009",
    "fetchedAt": "2026-04-20T01:54:17.307Z"
  },
  "Taric_sup": {
    "runes": [
      "8351",
      "8304",
      "8345",
      "8347",
      "8429",
      "8453"
    ],
    "items": [
      "3190",
      "3121",
      "3109"
    ],
    "starters": [
      "2003"
    ],
    "boots": "3047",
    "fetchedAt": "2026-04-20T01:54:19.482Z"
  },
  "Teemo_top": {
    "runes": [
      "8005",
      "9111",
      "9104",
      "8299",
      "8473",
      "8451"
    ],
    "items": [
      "3115",
      "6653",
      "3118"
    ],
    "starters": [
      "1056",
      "2003",
      "1055"
    ],
    "boots": "3009",
    "fetchedAt": "2026-04-20T01:54:21.715Z"
  },
  "Teemo_jg": {
    "runes": [
      "8005",
      "9111",
      "9104",
      "8299",
      "8473",
      "8451"
    ],
    "items": [
      "3115",
      "6653",
      "3118"
    ],
    "starters": [
      "1056",
      "2003",
      "1055"
    ],
    "boots": "3009",
    "fetchedAt": "2026-04-20T01:54:26.334Z"
  },
  "Thresh_sup": {
    "runes": [
      "8439",
      "8463",
      "8473",
      "8242",
      "8345",
      "8347"
    ],
    "items": [
      "3190",
      "3050",
      "3109"
    ],
    "starters": [
      "2003"
    ],
    "boots": "3009",
    "fetchedAt": "2026-04-20T01:54:28.414Z"
  },
  "Tristana_adc": {
    "runes": [
      "8008",
      "9111",
      "9104",
      "8017",
      "8304",
      "8345"
    ],
    "items": [
      "6676",
      "3031",
      "6675"
    ],
    "starters": [
      "1055",
      "2003",
      "1036"
    ],
    "boots": "3006",
    "fetchedAt": "2026-04-20T01:54:30.466Z"
  },
  "Trundle_jg": {
    "runes": [
      "8008",
      "9111",
      "9104",
      "8299",
      "8446",
      "8473"
    ],
    "items": [
      "3074",
      "3078",
      "3181"
    ],
    "starters": [
      "1055",
      "2003",
      "1054"
    ],
    "boots": "3047",
    "fetchedAt": "2026-04-20T01:54:32.442Z"
  },
  "Trundle_top": {
    "runes": [
      "8008",
      "9111",
      "9104",
      "8299",
      "8446",
      "8473"
    ],
    "items": [
      "3074",
      "3078",
      "3181"
    ],
    "starters": [
      "1055",
      "2003",
      "1054"
    ],
    "boots": "3047",
    "fetchedAt": "2026-04-20T01:54:34.841Z"
  },
  "Tryndamere_top": {
    "runes": [
      "9923",
      "8143",
      "8140",
      "8135",
      "9104",
      "8299"
    ],
    "items": [
      "3508",
      "3031",
      "6694"
    ],
    "starters": [
      "1055",
      "2003",
      "1054"
    ],
    "boots": "3006",
    "fetchedAt": "2026-04-20T01:54:37.003Z"
  },
  "TwistedFate_mid": {
    "runes": [
      "8229",
      "8226",
      "8234",
      "8237",
      "8473",
      "8242"
    ],
    "items": [
      "6657",
      "3100",
      "3094"
    ],
    "starters": [
      "1056",
      "2003",
      "1083"
    ],
    "boots": "3009",
    "fetchedAt": "2026-04-20T01:54:38.953Z"
  },
  "Twitch_adc": {
    "runes": [
      "8008",
      "9111",
      "9104",
      "8017",
      "8224",
      "8236"
    ],
    "items": [
      "6676",
      "2512",
      "3031"
    ],
    "starters": [
      "1055",
      "2003",
      "1056"
    ],
    "boots": "3006",
    "fetchedAt": "2026-04-20T01:54:40.933Z"
  },
  "Twitch_jg": {
    "runes": [
      "8008",
      "9111",
      "9104",
      "8017",
      "8224",
      "8236"
    ],
    "items": [
      "6676",
      "2512",
      "3031"
    ],
    "starters": [
      "1055",
      "2003",
      "1056"
    ],
    "boots": "3006",
    "fetchedAt": "2026-04-20T01:54:43.088Z"
  },
  "Urgot_top": {
    "runes": [
      "8005",
      "9111",
      "9105",
      "8299",
      "8473",
      "8451"
    ],
    "items": [
      "3071",
      "3053",
      "6665"
    ],
    "starters": [
      "1055",
      "2003",
      "1054"
    ],
    "boots": "3047",
    "fetchedAt": "2026-04-20T01:54:45.060Z"
  },
  "Vayne_adc": {
    "runes": [
      "8008",
      "9111",
      "9104",
      "8014",
      "8429",
      "8451"
    ],
    "items": [
      "3153",
      "3124",
      "3302"
    ],
    "starters": [
      "1055",
      "2003",
      "1054"
    ],
    "boots": "3006",
    "fetchedAt": "2026-04-20T01:54:47.030Z"
  },
  "Vayne_top": {
    "runes": [
      "8008",
      "9111",
      "9104",
      "8014",
      "8429",
      "8451"
    ],
    "items": [
      "3153",
      "3124",
      "3302"
    ],
    "starters": [
      "1055",
      "2003",
      "1054"
    ],
    "boots": "3006",
    "fetchedAt": "2026-04-20T01:54:49.615Z"
  },
  "Veigar_mid": {
    "runes": [
      "8369",
      "8304",
      "8345",
      "8347",
      "8226",
      "8210"
    ],
    "items": [
      "6657",
      "3040",
      "3089"
    ],
    "starters": [
      "1056",
      "2003",
      "3070"
    ],
    "boots": "3020",
    "fetchedAt": "2026-04-20T01:54:51.596Z"
  },
  "Veigar_adc": {
    "runes": [
      "8369",
      "8304",
      "8345",
      "8347",
      "8226",
      "8210"
    ],
    "items": [
      "6657",
      "3040",
      "3089"
    ],
    "starters": [
      "1056",
      "2003",
      "3070"
    ],
    "boots": "3020",
    "fetchedAt": "2026-04-20T01:54:53.723Z"
  },
  "Veigar_sup": {
    "runes": [
      "8369",
      "8304",
      "8345",
      "8347",
      "8226",
      "8210"
    ],
    "items": [
      "6657",
      "3040",
      "3089"
    ],
    "starters": [
      "1056",
      "2003",
      "3070"
    ],
    "boots": "3020",
    "fetchedAt": "2026-04-20T01:54:55.696Z"
  },
  "Vi_jg": {
    "runes": [
      "8010",
      "9111",
      "9105",
      "8014",
      "8304",
      "8347"
    ],
    "items": [
      "6610",
      "3071",
      "3026"
    ],
    "starters": [
      "1102",
      "2003",
      "1101"
    ],
    "boots": "3047",
    "fetchedAt": "2026-04-20T01:54:57.822Z"
  },
  "Viktor_mid": {
    "runes": [
      "8214",
      "8226",
      "8210",
      "8237",
      "8401",
      "8473"
    ],
    "items": [
      "2503",
      "6653",
      "3157"
    ],
    "starters": [
      "1056",
      "2003",
      "3070"
    ],
    "boots": "3020",
    "fetchedAt": "2026-04-20T01:54:59.956Z"
  },
  "Vladimir_mid": {
    "runes": [
      "8214",
      "8275",
      "8210",
      "8237",
      "9105",
      "8299"
    ],
    "items": [
      "3152",
      "4633",
      "3089"
    ],
    "starters": [
      "1056",
      "2003",
      "1082",
      "2031"
    ],
    "boots": "3020",
    "fetchedAt": "2026-04-20T01:55:01.890Z"
  },
  "Vladimir_top": {
    "runes": [
      "8214",
      "8275",
      "8210",
      "8237",
      "9105",
      "8299"
    ],
    "items": [
      "3152",
      "4633",
      "3089"
    ],
    "starters": [
      "1056",
      "2003",
      "1082",
      "2031"
    ],
    "boots": "3020",
    "fetchedAt": "2026-04-20T01:55:05.555Z"
  },
  "Volibear_top": {
    "runes": [
      "8008",
      "9111",
      "9105",
      "8299",
      "8446",
      "8453"
    ],
    "items": [
      "2510",
      "6675",
      "3065"
    ],
    "starters": [
      "1056",
      "2003",
      "1055"
    ],
    "boots": "3047",
    "fetchedAt": "2026-04-20T01:55:07.730Z"
  },
  "Volibear_jg": {
    "runes": [
      "8008",
      "9111",
      "9105",
      "8299",
      "8446",
      "8453"
    ],
    "items": [
      "2510",
      "6675",
      "3065"
    ],
    "starters": [
      "1056",
      "2003",
      "1055"
    ],
    "boots": "3047",
    "fetchedAt": "2026-04-20T01:55:09.643Z"
  },
  "Warwick_jg": {
    "runes": [
      "8008",
      "9111",
      "9104",
      "8299",
      "8234",
      "8232"
    ],
    "items": [
      "6631",
      "3153",
      "3075"
    ],
    "starters": [
      "1102",
      "2003"
    ],
    "boots": "3047",
    "fetchedAt": "2026-04-20T01:55:11.674Z"
  },
  "Warwick_top": {
    "runes": [
      "8008",
      "9111",
      "9104",
      "8299",
      "8234",
      "8232"
    ],
    "items": [
      "6631",
      "3153",
      "3075"
    ],
    "starters": [
      "1102",
      "2003"
    ],
    "boots": "3047",
    "fetchedAt": "2026-04-20T01:55:15.297Z"
  },
  "Xayah_adc": {
    "runes": [
      "8008",
      "8009",
      "9103",
      "8014",
      "8304",
      "8345"
    ],
    "items": [
      "3508",
      "6675",
      "3031"
    ],
    "starters": [
      "1055",
      "2003"
    ],
    "boots": "3006",
    "fetchedAt": "2026-04-20T01:55:17.273Z"
  },
  "Xerath_mid": {
    "runes": [
      "8229",
      "8226",
      "8210",
      "8237",
      "8009",
      "8014"
    ],
    "items": [
      "6655",
      "4645",
      "3089"
    ],
    "starters": [
      "1056",
      "2003",
      "1082",
      "2031"
    ],
    "boots": "3020",
    "fetchedAt": "2026-04-20T01:55:20.649Z"
  },
  "Xerath_sup": {
    "runes": [
      "8229",
      "8226",
      "8210",
      "8237",
      "8009",
      "8014"
    ],
    "items": [
      "6655",
      "4645",
      "3089"
    ],
    "starters": [
      "1056",
      "2003",
      "1082",
      "2031"
    ],
    "boots": "3020",
    "fetchedAt": "2026-04-20T01:55:22.792Z"
  },
  "XinZhao_jg": {
    "runes": [
      "8010",
      "9111",
      "9104",
      "8014",
      "8304",
      "8347"
    ],
    "items": [
      "6610",
      "3071",
      "6333"
    ],
    "starters": [
      "1102",
      "2003",
      "1101"
    ],
    "boots": "3047",
    "fetchedAt": "2026-04-20T01:55:24.751Z"
  },
  "Yasuo_mid": {
    "runes": [
      "8008",
      "9101",
      "9104",
      "8299",
      "8444",
      "8451"
    ],
    "items": [
      "3153",
      "6673",
      "3031"
    ],
    "starters": [
      "1055",
      "2003",
      "1054"
    ],
    "boots": "3006",
    "fetchedAt": "2026-04-20T01:55:26.740Z"
  },
  "Yasuo_top": {
    "runes": [
      "8008",
      "9101",
      "9104",
      "8299",
      "8444",
      "8451"
    ],
    "items": [
      "3153",
      "6673",
      "3031"
    ],
    "starters": [
      "1055",
      "2003",
      "1054"
    ],
    "boots": "3006",
    "fetchedAt": "2026-04-20T01:55:28.680Z"
  },
  "Yasuo_adc": {
    "runes": [
      "8008",
      "9101",
      "9104",
      "8299",
      "8444",
      "8451"
    ],
    "items": [
      "3153",
      "6673",
      "3031"
    ],
    "starters": [
      "1055",
      "2003",
      "1054"
    ],
    "boots": "3006",
    "fetchedAt": "2026-04-20T01:55:30.588Z"
  },
  "Yone_mid": {
    "runes": [
      "8008",
      "9101",
      "9104",
      "8299",
      "8444",
      "8451"
    ],
    "items": [
      "3153",
      "6673",
      "3031"
    ],
    "starters": [
      "1055",
      "2003",
      "1054"
    ],
    "boots": "3006",
    "fetchedAt": "2026-04-20T01:55:32.902Z"
  },
  "Yone_top": {
    "runes": [
      "8008",
      "9101",
      "9104",
      "8299",
      "8444",
      "8451"
    ],
    "items": [
      "3153",
      "6673",
      "3031"
    ],
    "starters": [
      "1055",
      "2003",
      "1054"
    ],
    "boots": "3006",
    "fetchedAt": "2026-04-20T01:55:35.090Z"
  },
  "Yorick_top": {
    "runes": [
      "8437",
      "8446",
      "8473",
      "8451",
      "8009",
      "9103"
    ],
    "items": [
      "3078",
      "3161",
      "6694"
    ],
    "starters": [
      "1054",
      "2003",
      "1055"
    ],
    "boots": "3047",
    "fetchedAt": "2026-04-20T01:55:37.105Z"
  },
  "Yuumi_sup": {
    "runes": [
      "8214",
      "8226",
      "8210",
      "8237",
      "8463",
      "8453"
    ],
    "items": [
      "3222",
      "6617",
      "3504"
    ],
    "starters": [
      "2003"
    ],
    "boots": "3009",
    "fetchedAt": "2026-04-20T01:55:39.274Z"
  },
  "Zac_jg": {
    "runes": [
      "8439",
      "8463",
      "8429",
      "8453",
      "9111",
      "9105"
    ],
    "items": [
      "3152",
      "3068",
      "3065"
    ],
    "starters": [
      "1101",
      "1103",
      "2003"
    ],
    "boots": "3111",
    "fetchedAt": "2026-04-20T01:55:41.419Z"
  },
  "Zac_top": {
    "runes": [
      "8439",
      "8463",
      "8429",
      "8453",
      "9111",
      "9105"
    ],
    "items": [
      "3152",
      "3068",
      "3065"
    ],
    "starters": [
      "1101",
      "1103",
      "2003"
    ],
    "boots": "3111",
    "fetchedAt": "2026-04-20T01:55:43.388Z"
  },
  "Zed_mid": {
    "runes": [
      "8112",
      "8139",
      "8140",
      "8106",
      "8210",
      "8237"
    ],
    "items": [
      "6692",
      "6699",
      "6694"
    ],
    "starters": [
      "1036",
      "2003",
      "1055"
    ],
    "boots": "3111",
    "fetchedAt": "2026-04-20T01:55:46.589Z"
  },
  "Zed_jg": {
    "runes": [
      "8112",
      "8139",
      "8140",
      "8106",
      "8210",
      "8237"
    ],
    "items": [
      "6692",
      "6699",
      "6694"
    ],
    "starters": [
      "1036",
      "2003",
      "1055"
    ],
    "boots": "3111",
    "fetchedAt": "2026-04-20T01:55:48.730Z"
  },
  "Ziggs_mid": {
    "runes": [
      "8229",
      "8226",
      "8210",
      "8237",
      "8304",
      "8345"
    ],
    "items": [
      "6655",
      "4628",
      "4645"
    ],
    "starters": [
      "1056",
      "2003",
      "3070"
    ],
    "boots": "3020",
    "fetchedAt": "2026-04-20T01:55:50.750Z"
  },
  "Ziggs_adc": {
    "runes": [
      "8229",
      "8226",
      "8210",
      "8237",
      "8304",
      "8345"
    ],
    "items": [
      "6655",
      "4628",
      "4645"
    ],
    "starters": [
      "1056",
      "2003",
      "3070"
    ],
    "boots": "3020",
    "fetchedAt": "2026-04-20T01:55:52.730Z"
  },
  "Zilean_sup": {
    "runes": [
      "8214",
      "8226",
      "8210",
      "8232",
      "8126",
      "8105"
    ],
    "items": [
      "2065",
      "2524",
      "4005"
    ],
    "starters": [
      "2003"
    ],
    "boots": "3009",
    "fetchedAt": "2026-04-20T01:55:55.251Z"
  },
  "Zilean_mid": {
    "runes": [
      "8214",
      "8226",
      "8210",
      "8232",
      "8126",
      "8105"
    ],
    "items": [
      "2065",
      "2524",
      "4005"
    ],
    "starters": [
      "2003"
    ],
    "boots": "3009",
    "fetchedAt": "2026-04-20T01:55:57.571Z"
  },
  "Zoe_mid": {
    "runes": [
      "8112",
      "8143",
      "8140",
      "8105",
      "8275",
      "8210"
    ],
    "items": [
      "6655",
      "4645",
      "3089"
    ],
    "starters": [
      "1056",
      "2003",
      "1082",
      "2031"
    ],
    "boots": "3020",
    "fetchedAt": "2026-04-20T01:55:59.534Z"
  },
  "Zoe_sup": {
    "runes": [
      "8112",
      "8143",
      "8140",
      "8105",
      "8275",
      "8210"
    ],
    "items": [
      "6655",
      "4645",
      "3089"
    ],
    "starters": [
      "1056",
      "2003",
      "1082",
      "2031"
    ],
    "boots": "3020",
    "fetchedAt": "2026-04-20T01:56:01.457Z"
  },
  "Zyra_sup": {
    "runes": [
      "8229",
      "8226",
      "8210",
      "8237",
      "8139",
      "8105"
    ],
    "items": [
      "6653",
      "3116",
      "3165"
    ],
    "starters": [
      "2003"
    ],
    "boots": "3020",
    "fetchedAt": "2026-04-20T01:56:04.695Z"
  },
  "Zyra_mid": {
    "runes": [
      "8229",
      "8226",
      "8210",
      "8237",
      "8139",
      "8105"
    ],
    "items": [
      "6653",
      "3116",
      "3165"
    ],
    "starters": [
      "2003"
    ],
    "boots": "3020",
    "fetchedAt": "2026-04-20T01:56:07.626Z"
  },
  "Zyra_jg": {
    "runes": [
      "8229",
      "8226",
      "8210",
      "8237",
      "8139",
      "8105"
    ],
    "items": [
      "6653",
      "3116",
      "3165"
    ],
    "starters": [
      "2003"
    ],
    "boots": "3020",
    "fetchedAt": "2026-04-20T01:56:09.695Z"
  },
  "Mel_mid": {
    "runes": [
      "8229",
      "8226",
      "8210",
      "8237",
      "8009",
      "8014"
    ],
    "items": [
      "6655",
      "4645",
      "3157"
    ],
    "starters": [
      "1056",
      "2003",
      "3070"
    ],
    "boots": "3020",
    "fetchedAt": "2026-04-20T01:56:11.643Z"
  },
  "Mel_adc": {
    "runes": [
      "8229",
      "8226",
      "8210",
      "8237",
      "8009",
      "8014"
    ],
    "items": [
      "6655",
      "4645",
      "3157"
    ],
    "starters": [
      "1056",
      "2003",
      "3070"
    ],
    "boots": "3020",
    "fetchedAt": "2026-04-20T01:56:13.605Z"
  },
  "Mel_sup": {
    "runes": [
      "8229",
      "8226",
      "8210",
      "8237",
      "8009",
      "8014"
    ],
    "items": [
      "6655",
      "4645",
      "3157"
    ],
    "starters": [
      "1056",
      "2003",
      "3070"
    ],
    "boots": "3020",
    "fetchedAt": "2026-04-20T01:56:15.544Z"
  },
  "Sion_top": {
    "runes": [
      "8437",
      "8446",
      "8429",
      "8451",
      "8321",
      "8410"
    ],
    "items": [
      "6664",
      "2502",
      "6665"
    ],
    "starters": [
      "1054",
      "2003",
      "1083"
    ],
    "boots": "3047",
    "fetchedAt": "2026-04-20T01:56:33.638Z"
  },
  "Sion_sup": {
    "runes": [
      "8437",
      "8446",
      "8429",
      "8451",
      "8321",
      "8410"
    ],
    "items": [
      "6664",
      "2502",
      "6665"
    ],
    "starters": [
      "1054",
      "2003",
      "1083"
    ],
    "boots": "3047",
    "fetchedAt": "2026-04-20T01:56:35.739Z"
  },
  "Nasus_top": {
    "runes": [
      "8021",
      "9111",
      "9105",
      "8299",
      "8444",
      "8242"
    ],
    "items": [
      "3078",
      "3110",
      "3065"
    ],
    "starters": [
      "1054",
      "2003",
      "1056"
    ],
    "boots": "3047",
    "fetchedAt": "2026-04-20T01:56:38.144Z"
  },
  "Nasus_jg": {
    "runes": [
      "8021",
      "9111",
      "9105",
      "8299",
      "8444",
      "8242"
    ],
    "items": [
      "3078",
      "3110",
      "3065"
    ],
    "starters": [
      "1054",
      "2003",
      "1056"
    ],
    "boots": "3047",
    "fetchedAt": "2026-04-20T01:56:40.066Z"
  },
  "Nasus_mid": {
    "runes": [
      "8021",
      "9111",
      "9105",
      "8299",
      "8444",
      "8242"
    ],
    "items": [
      "3078",
      "3110",
      "3065"
    ],
    "starters": [
      "1054",
      "2003",
      "1056"
    ],
    "boots": "3047",
    "fetchedAt": "2026-04-20T01:56:42.047Z"
  },
  "Chogath_top": {
    "runes": [
      "9923",
      "8126",
      "8140",
      "8106",
      "8224",
      "8234"
    ],
    "items": [
      "3152",
      "4633",
      "3742"
    ],
    "starters": [
      "1056",
      "2003",
      "1054"
    ],
    "boots": "3047",
    "fetchedAt": "2026-04-20T01:56:44.744Z"
  },
  "Chogath_jg": {
    "runes": [
      "9923",
      "8126",
      "8140",
      "8106",
      "8224",
      "8234"
    ],
    "items": [
      "3152",
      "4633",
      "3742"
    ],
    "starters": [
      "1056",
      "2003",
      "1054"
    ],
    "boots": "3047",
    "fetchedAt": "2026-04-20T01:56:46.700Z"
  },
  "Chogath_mid": {
    "runes": [
      "9923",
      "8126",
      "8140",
      "8106",
      "8224",
      "8234"
    ],
    "items": [
      "3152",
      "4633",
      "3742"
    ],
    "starters": [
      "1056",
      "2003",
      "1054"
    ],
    "boots": "3047",
    "fetchedAt": "2026-04-20T01:56:48.675Z"
  },
  "Gangplank_top": {
    "runes": [
      "8369",
      "8321",
      "8313",
      "8347",
      "9105",
      "8017"
    ],
    "items": [
      "3508",
      "6676",
      "3031"
    ],
    "starters": [
      "1055",
      "2003",
      "1054"
    ],
    "boots": "3047",
    "fetchedAt": "2026-04-20T01:56:50.644Z"
  },
  "DrMundo_top": {
    "runes": [
      "8437",
      "8446",
      "8444",
      "8451",
      "8304",
      "8410"
    ],
    "items": [
      "3083",
      "3084",
      "3748"
    ],
    "starters": [
      "1054",
      "2003",
      "1028"
    ],
    "boots": "3009",
    "fetchedAt": "2026-04-20T01:56:52.579Z"
  },
  "DrMundo_jg": {
    "runes": [
      "8437",
      "8446",
      "8444",
      "8451",
      "8304",
      "8410"
    ],
    "items": [
      "3083",
      "3084",
      "3748"
    ],
    "starters": [
      "1054",
      "2003",
      "1028"
    ],
    "boots": "3009",
    "fetchedAt": "2026-04-20T01:56:54.853Z"
  },
  "Illaoi_top": {
    "runes": [
      "8437",
      "8446",
      "8473",
      "8451",
      "8009",
      "8299"
    ],
    "items": [
      "3071",
      "6662",
      "3053"
    ],
    "starters": [
      "1054",
      "2003",
      "1055"
    ],
    "boots": "3047",
    "fetchedAt": "2026-04-20T01:56:56.759Z"
  },
  "Gragas_jg": {
    "runes": [
      "8230",
      "8226",
      "8210",
      "8237",
      "8345",
      "8347"
    ],
    "items": [
      "6657",
      "3121",
      "4629"
    ],
    "starters": [
      "1056",
      "2003",
      "3070"
    ],
    "boots": "3020",
    "fetchedAt": "2026-04-20T01:56:59.089Z"
  },
  "Gragas_top": {
    "runes": [
      "8230",
      "8226",
      "8210",
      "8237",
      "8345",
      "8347"
    ],
    "items": [
      "6657",
      "3121",
      "4629"
    ],
    "starters": [
      "1056",
      "2003",
      "3070"
    ],
    "boots": "3020",
    "fetchedAt": "2026-04-20T01:57:01.218Z"
  },
  "Gragas_mid": {
    "runes": [
      "8230",
      "8226",
      "8210",
      "8237",
      "8345",
      "8347"
    ],
    "items": [
      "6657",
      "3121",
      "4629"
    ],
    "starters": [
      "1056",
      "2003",
      "3070"
    ],
    "boots": "3020",
    "fetchedAt": "2026-04-20T01:57:03.341Z"
  },
  "MonkeyKing_jg": {
    "runes": [
      "8010",
      "9111",
      "9104",
      "8299",
      "8304",
      "8347"
    ],
    "items": [
      "3078",
      "6610",
      "3071"
    ],
    "starters": [
      "1102",
      "2003",
      "1101"
    ],
    "boots": "3047",
    "fetchedAt": "2026-04-20T01:57:05.261Z"
  },
  "MonkeyKing_top": {
    "runes": [
      "8010",
      "9111",
      "9104",
      "8299",
      "8304",
      "8347"
    ],
    "items": [
      "3078",
      "6610",
      "3071"
    ],
    "starters": [
      "1102",
      "2003",
      "1101"
    ],
    "boots": "3047",
    "fetchedAt": "2026-04-20T01:57:07.373Z"
  },
  "Rumble_top": {
    "runes": [
      "8229",
      "8275",
      "8233",
      "8237",
      "8473",
      "8242"
    ],
    "items": [
      "6653",
      "8010",
      "3157"
    ],
    "starters": [
      "1056",
      "2003",
      "1054"
    ],
    "boots": "3009",
    "fetchedAt": "2026-04-20T01:57:09.575Z"
  },
  "Rumble_jg": {
    "runes": [
      "8229",
      "8275",
      "8233",
      "8237",
      "8473",
      "8242"
    ],
    "items": [
      "6653",
      "8010",
      "3157"
    ],
    "starters": [
      "1056",
      "2003",
      "1054"
    ],
    "boots": "3009",
    "fetchedAt": "2026-04-20T01:57:11.498Z"
  },
  "Kayle_top": {
    "runes": [
      "8005",
      "9101",
      "9104",
      "8299",
      "8234",
      "8236"
    ],
    "items": [
      "3115",
      "2510",
      "3089"
    ],
    "starters": [
      "1055",
      "2003",
      "1054"
    ],
    "boots": "3006",
    "fetchedAt": "2026-04-20T01:57:13.448Z"
  },
  "Kayle_mid": {
    "runes": [
      "8005",
      "9101",
      "9104",
      "8299",
      "8234",
      "8236"
    ],
    "items": [
      "3115",
      "2510",
      "3089"
    ],
    "starters": [
      "1055",
      "2003",
      "1054"
    ],
    "boots": "3006",
    "fetchedAt": "2026-04-20T01:57:15.424Z"
  },
  "Singed_top": {
    "runes": [
      "8010",
      "9111",
      "9104",
      "8299",
      "8275",
      "8234"
    ],
    "items": [
      "6653",
      "3116",
      "2525"
    ],
    "starters": [
      "1056",
      "2003",
      "1082",
      "2031"
    ],
    "boots": "3009",
    "fetchedAt": "2026-04-20T01:57:17.385Z"
  },
  "Ornn_top": {
    "runes": [
      "8437",
      "8446",
      "8473",
      "8451",
      "8304",
      "8345"
    ],
    "items": [
      "3068",
      "3075",
      "6665"
    ],
    "starters": [
      "1054",
      "2003",
      "2031"
    ],
    "boots": "3047",
    "fetchedAt": "2026-04-20T01:57:19.541Z"
  },
  "Mordekaiser_top": {
    "runes": [
      "8010",
      "9111",
      "9105",
      "8299",
      "8473",
      "8453"
    ],
    "items": [
      "3116",
      "4633",
      "6653"
    ],
    "starters": [
      "1056",
      "2003",
      "1054"
    ],
    "boots": "3047",
    "fetchedAt": "2026-04-20T01:57:21.524Z"
  },
  "Mordekaiser_mid": {
    "runes": [
      "8010",
      "9111",
      "9105",
      "8299",
      "8473",
      "8453"
    ],
    "items": [
      "3116",
      "4633",
      "6653"
    ],
    "starters": [
      "1056",
      "2003",
      "1054"
    ],
    "boots": "3047",
    "fetchedAt": "2026-04-20T01:57:23.476Z"
  },
  "Mordekaiser_jg": {
    "runes": [
      "8010",
      "9111",
      "9105",
      "8299",
      "8473",
      "8453"
    ],
    "items": [
      "3116",
      "4633",
      "6653"
    ],
    "starters": [
      "1056",
      "2003",
      "1054"
    ],
    "boots": "3047",
    "fetchedAt": "2026-04-20T01:57:25.745Z"
  },
  "Sett_top": {
    "runes": [
      "8010",
      "9111",
      "9104",
      "8299",
      "8444",
      "8242"
    ],
    "items": [
      "6631",
      "2501",
      "3053"
    ],
    "starters": [
      "1055",
      "2003",
      "1054"
    ],
    "boots": "3047",
    "fetchedAt": "2026-04-20T01:57:27.709Z"
  },
  "Sett_jg": {
    "runes": [
      "8010",
      "9111",
      "9104",
      "8299",
      "8444",
      "8242"
    ],
    "items": [
      "6631",
      "2501",
      "3053"
    ],
    "starters": [
      "1055",
      "2003",
      "1054"
    ],
    "boots": "3047",
    "fetchedAt": "2026-04-20T01:57:29.665Z"
  },
  "Sett_sup": {
    "runes": [
      "8010",
      "9111",
      "9104",
      "8299",
      "8444",
      "8242"
    ],
    "items": [
      "6631",
      "2501",
      "3053"
    ],
    "starters": [
      "1055",
      "2003",
      "1054"
    ],
    "boots": "3047",
    "fetchedAt": "2026-04-20T01:57:32.561Z"
  },
  "RekSai_jg": {
    "runes": [
      "8010",
      "9111",
      "9104",
      "8014",
      "8304",
      "8347"
    ],
    "items": [
      "6631",
      "3161",
      "3053"
    ],
    "starters": [
      "1101",
      "2003"
    ],
    "boots": "3047",
    "fetchedAt": "2026-04-20T01:57:34.572Z"
  },
  "Sylas_mid": {
    "runes": [
      "8010",
      "8009",
      "9105",
      "8299",
      "8444",
      "8242"
    ],
    "items": [
      "3152",
      "4633",
      "3157"
    ],
    "starters": [
      "1056",
      "2003",
      "1054"
    ],
    "boots": "3020",
    "fetchedAt": "2026-04-20T01:57:36.546Z"
  },
  "Sylas_top": {
    "runes": [
      "8010",
      "8009",
      "9105",
      "8299",
      "8444",
      "8242"
    ],
    "items": [
      "3152",
      "4633",
      "3157"
    ],
    "starters": [
      "1056",
      "2003",
      "1054"
    ],
    "boots": "3020",
    "fetchedAt": "2026-04-20T01:57:39.247Z"
  },
  "Sylas_jg": {
    "runes": [
      "8010",
      "8009",
      "9105",
      "8299",
      "8444",
      "8242"
    ],
    "items": [
      "3152",
      "4633",
      "3157"
    ],
    "starters": [
      "1056",
      "2003",
      "1054"
    ],
    "boots": "3020",
    "fetchedAt": "2026-04-20T01:57:41.174Z"
  },
  "Kassadin_mid": {
    "runes": [
      "8369",
      "8321",
      "8313",
      "8347",
      "8143",
      "8106"
    ],
    "items": [
      "6657",
      "3042",
      "3040"
    ],
    "starters": [
      "1082",
      "2031",
      "1054",
      "2003"
    ],
    "boots": "3020",
    "fetchedAt": "2026-04-20T01:57:43.117Z"
  },
  "Jhin_adc": {
    "runes": [
      "8021",
      "8009",
      "9103",
      "8014",
      "8234",
      "8236"
    ],
    "items": [
      "6697",
      "6676",
      "3031"
    ],
    "starters": [
      "1055",
      "2003",
      "1036",
      "2031"
    ],
    "boots": "3009",
    "fetchedAt": "2026-04-20T01:57:45.226Z"
  },
  "Varus_adc": {
    "runes": [
      "8229",
      "8226",
      "8210",
      "8237",
      "8321",
      "8313"
    ],
    "items": [
      "3142",
      "3042",
      "3814"
    ],
    "starters": [
      "1055",
      "2003",
      "3070"
    ],
    "boots": "3006",
    "fetchedAt": "2026-04-20T01:57:47.202Z"
  },
  "Varus_sup": {
    "runes": [
      "8229",
      "8226",
      "8210",
      "8237",
      "8321",
      "8313"
    ],
    "items": [
      "3142",
      "3042",
      "3814"
    ],
    "starters": [
      "1055",
      "2003",
      "3070"
    ],
    "boots": "3006",
    "fetchedAt": "2026-04-20T01:57:49.341Z"
  },
  "Varus_top": {
    "runes": [
      "8229",
      "8226",
      "8210",
      "8237",
      "8321",
      "8313"
    ],
    "items": [
      "3142",
      "3042",
      "3814"
    ],
    "starters": [
      "1055",
      "2003",
      "3070"
    ],
    "boots": "3006",
    "fetchedAt": "2026-04-20T01:57:51.757Z"
  },
  "Ekko_mid": {
    "runes": [
      "8128",
      "8143",
      "8140",
      "8135",
      "8304",
      "8347"
    ],
    "items": [
      "2510",
      "4645",
      "3089"
    ],
    "starters": [
      "1101",
      "2003",
      "1102"
    ],
    "boots": "3020",
    "fetchedAt": "2026-04-20T01:57:53.669Z"
  },
  "Ekko_jg": {
    "runes": [
      "8128",
      "8143",
      "8140",
      "8135",
      "8304",
      "8347"
    ],
    "items": [
      "2510",
      "4645",
      "3089"
    ],
    "starters": [
      "1101",
      "2003",
      "1102"
    ],
    "boots": "3020",
    "fetchedAt": "2026-04-20T01:57:56.295Z"
  },
  "Poppy_top": {
    "runes": [
      "8439",
      "8463",
      "8473",
      "8242",
      "8306",
      "8347"
    ],
    "items": [
      "3742",
      "3190",
      "2524"
    ],
    "starters": [
      "2003"
    ],
    "boots": "3009",
    "fetchedAt": "2026-04-20T01:57:59.207Z"
  },
  "Poppy_jg": {
    "runes": [
      "8439",
      "8463",
      "8473",
      "8242",
      "8306",
      "8347"
    ],
    "items": [
      "3742",
      "3190",
      "2524"
    ],
    "starters": [
      "2003"
    ],
    "boots": "3009",
    "fetchedAt": "2026-04-20T01:58:01.185Z"
  },
  "Poppy_sup": {
    "runes": [
      "8439",
      "8463",
      "8473",
      "8242",
      "8306",
      "8347"
    ],
    "items": [
      "3742",
      "3190",
      "2524"
    ],
    "starters": [
      "2003"
    ],
    "boots": "3009",
    "fetchedAt": "2026-04-20T01:58:03.144Z"
  },
  "Gnar_top": {
    "runes": [
      "8021",
      "9111",
      "9104",
      "8299",
      "8473",
      "8451"
    ],
    "items": [
      "3078",
      "3071",
      "3053"
    ],
    "starters": [
      "1055",
      "2003",
      "1054"
    ],
    "boots": "3047",
    "fetchedAt": "2026-04-20T01:58:05.094Z"
  },
  "Kennen_top": {
    "runes": [
      "8112",
      "8139",
      "8140",
      "8106",
      "8233",
      "8237"
    ],
    "items": [
      "3152",
      "4645",
      "3157"
    ],
    "starters": [
      "1055",
      "2003",
      "1056"
    ],
    "boots": "3020",
    "fetchedAt": "2026-04-20T01:58:07.215Z"
  },
  "Kennen_mid": {
    "runes": [
      "8112",
      "8139",
      "8140",
      "8106",
      "8233",
      "8237"
    ],
    "items": [
      "3152",
      "4645",
      "3157"
    ],
    "starters": [
      "1055",
      "2003",
      "1056"
    ],
    "boots": "3020",
    "fetchedAt": "2026-04-20T01:58:09.224Z"
  },
  "Corki_adc": {
    "runes": [
      "8010",
      "8009",
      "9104",
      "8017",
      "8321",
      "8313"
    ],
    "items": [
      "3078",
      "3042",
      "6676"
    ],
    "starters": [
      "1055",
      "2003",
      "3070"
    ],
    "boots": "3047",
    "fetchedAt": "2026-04-20T01:58:11.418Z"
  },
  "Corki_mid": {
    "runes": [
      "8010",
      "8009",
      "9104",
      "8017",
      "8321",
      "8313"
    ],
    "items": [
      "3078",
      "3042",
      "6676"
    ],
    "starters": [
      "1055",
      "2003",
      "3070"
    ],
    "boots": "3047",
    "fetchedAt": "2026-04-20T01:58:13.552Z"
  },
  "KogMaw_adc": {
    "runes": [
      "8008",
      "9111",
      "9103",
      "8299",
      "8429",
      "8451"
    ],
    "items": [
      "3153",
      "3124",
      "3085"
    ],
    "starters": [
      "1055",
      "2003",
      "1056"
    ],
    "boots": "3006",
    "fetchedAt": "2026-04-20T01:58:15.502Z"
  },
  "KogMaw_mid": {
    "runes": [
      "8008",
      "9111",
      "9103",
      "8299",
      "8429",
      "8451"
    ],
    "items": [
      "3153",
      "3124",
      "3085"
    ],
    "starters": [
      "1055",
      "2003",
      "1056"
    ],
    "boots": "3006",
    "fetchedAt": "2026-04-20T01:58:18.251Z"
  },
  "Aphelios_adc": {
    "runes": [
      "8005",
      "9111",
      "9103",
      "8017",
      "8321",
      "8313"
    ],
    "items": [
      "2523",
      "3031",
      "3036"
    ],
    "starters": [
      "1055",
      "2003",
      "1083"
    ],
    "boots": "3006",
    "fetchedAt": "2026-04-20T01:58:20.607Z"
  },
  "Zeri_adc": {
    "runes": [
      "8008",
      "9111",
      "9103",
      "8017",
      "8321",
      "8313"
    ],
    "items": [
      "3032",
      "2512",
      "3031"
    ],
    "starters": [
      "1055",
      "2003",
      "1083"
    ],
    "boots": "3006",
    "fetchedAt": "2026-04-20T01:58:22.694Z"
  },
  "Nilah_adc": {
    "runes": [
      "8010",
      "9111",
      "9104",
      "8299",
      "8321",
      "8347"
    ],
    "items": [
      "6676",
      "3031",
      "3036"
    ],
    "starters": [
      "1055",
      "2003",
      "1054"
    ],
    "boots": "3006",
    "fetchedAt": "2026-04-20T01:58:24.971Z"
  },
  "Evelynn_jg": {
    "runes": [
      "8112",
      "8143",
      "8140",
      "8105",
      "8233",
      "8236"
    ],
    "items": [
      "3100",
      "3041",
      "3089"
    ],
    "starters": [
      "1102",
      "2003"
    ],
    "boots": "3009",
    "fetchedAt": "2026-04-20T01:58:26.953Z"
  },
  "Kayn_jg": {
    "runes": [
      "8128",
      "8143",
      "8140",
      "8135",
      "8304",
      "8347"
    ],
    "items": [
      "6697",
      "6696",
      "6694"
    ],
    "starters": [
      "1102",
      "2003"
    ],
    "boots": "3047",
    "fetchedAt": "2026-04-20T01:58:28.928Z"
  },
  "Fiddlesticks_jg": {
    "runes": [
      "8112",
      "8126",
      "8140",
      "8106",
      "8224",
      "8210"
    ],
    "items": [
      "3118",
      "6653",
      "3157"
    ],
    "starters": [
      "1102",
      "2003"
    ],
    "boots": "3020",
    "fetchedAt": "2026-04-20T01:58:31.037Z"
  },
  "Fiddlesticks_sup": {
    "runes": [
      "8112",
      "8126",
      "8140",
      "8106",
      "8224",
      "8210"
    ],
    "items": [
      "3118",
      "6653",
      "3157"
    ],
    "starters": [
      "1102",
      "2003"
    ],
    "boots": "3020",
    "fetchedAt": "2026-04-20T01:58:33.157Z"
  },
  "Udyr_jg": {
    "runes": [
      "8010",
      "9111",
      "9105",
      "8299",
      "8304",
      "8410"
    ],
    "items": [
      "6653",
      "3742",
      "3065"
    ],
    "starters": [
      "1102",
      "2003"
    ],
    "boots": "3009",
    "fetchedAt": "2026-04-20T01:58:35.109Z"
  },
  "Udyr_top": {
    "runes": [
      "8010",
      "9111",
      "9105",
      "8299",
      "8304",
      "8410"
    ],
    "items": [
      "6653",
      "3742",
      "3065"
    ],
    "starters": [
      "1102",
      "2003"
    ],
    "boots": "3009",
    "fetchedAt": "2026-04-20T01:58:37.261Z"
  },
  "Galio_mid": {
    "runes": [
      "8230",
      "8226",
      "8210",
      "8237",
      "8444",
      "8242"
    ],
    "items": [
      "6664",
      "4633",
      "3157"
    ],
    "starters": [
      "1056",
      "2003",
      "1054"
    ],
    "boots": "3047",
    "fetchedAt": "2026-04-20T01:58:39.268Z"
  },
  "Galio_sup": {
    "runes": [
      "8230",
      "8226",
      "8210",
      "8237",
      "8444",
      "8242"
    ],
    "items": [
      "6664",
      "4633",
      "3157"
    ],
    "starters": [
      "1056",
      "2003",
      "1054"
    ],
    "boots": "3047",
    "fetchedAt": "2026-04-20T01:58:41.207Z"
  },
  "Lissandra_mid": {
    "runes": [
      "8112",
      "8126",
      "8140",
      "8106",
      "8226",
      "8210"
    ],
    "items": [
      "3118",
      "4645",
      "3157"
    ],
    "starters": [
      "1056",
      "2003",
      "1082",
      "2031"
    ],
    "boots": "3020",
    "fetchedAt": "2026-04-20T01:58:43.646Z"
  },
  "Lissandra_top": {
    "runes": [
      "8112",
      "8126",
      "8140",
      "8106",
      "8226",
      "8210"
    ],
    "items": [
      "3118",
      "4645",
      "3157"
    ],
    "starters": [
      "1056",
      "2003",
      "1082",
      "2031"
    ],
    "boots": "3020",
    "fetchedAt": "2026-04-20T01:58:45.777Z"
  },
  "Malzahar_mid": {
    "runes": [
      "8229",
      "8226",
      "8210",
      "8236",
      "8304",
      "8347"
    ],
    "items": [
      "2503",
      "6653",
      "3116"
    ],
    "starters": [
      "1056",
      "2003",
      "3070"
    ],
    "boots": "3020",
    "fetchedAt": "2026-04-20T01:58:47.767Z"
  },
  "Malzahar_sup": {
    "runes": [
      "8229",
      "8226",
      "8210",
      "8236",
      "8304",
      "8347"
    ],
    "items": [
      "2503",
      "6653",
      "3116"
    ],
    "starters": [
      "1056",
      "2003",
      "3070"
    ],
    "boots": "3020",
    "fetchedAt": "2026-04-20T01:58:49.894Z"
  },
  "Velkoz_mid": {
    "runes": [
      "8229",
      "8226",
      "8210",
      "8237",
      "8126",
      "8106"
    ],
    "items": [
      "6655",
      "4628",
      "4645"
    ],
    "starters": [
      "2003"
    ],
    "boots": "3020",
    "fetchedAt": "2026-04-20T01:58:51.863Z"
  },
  "Velkoz_sup": {
    "runes": [
      "8229",
      "8226",
      "8210",
      "8237",
      "8126",
      "8106"
    ],
    "items": [
      "6655",
      "4628",
      "4645"
    ],
    "starters": [
      "2003"
    ],
    "boots": "3020",
    "fetchedAt": "2026-04-20T01:58:53.831Z"
  },
  "Velkoz_adc": {
    "runes": [
      "8229",
      "8226",
      "8210",
      "8237",
      "8126",
      "8106"
    ],
    "items": [
      "6655",
      "4628",
      "4645"
    ],
    "starters": [
      "2003"
    ],
    "boots": "3020",
    "fetchedAt": "2026-04-20T01:58:55.748Z"
  },
  "Taliyah_mid": {
    "runes": [
      "8230",
      "8226",
      "8210",
      "8237",
      "8009",
      "9105"
    ],
    "items": [
      "3040",
      "3116",
      "6653"
    ],
    "starters": [
      "1056",
      "2003",
      "3070"
    ],
    "boots": "3020",
    "fetchedAt": "2026-04-20T01:58:57.671Z"
  },
  "Taliyah_jg": {
    "runes": [
      "8230",
      "8226",
      "8210",
      "8237",
      "8009",
      "9105"
    ],
    "items": [
      "3040",
      "3116",
      "6653"
    ],
    "starters": [
      "1056",
      "2003",
      "3070"
    ],
    "boots": "3020",
    "fetchedAt": "2026-04-20T01:58:59.583Z"
  },
  "Ryze_mid": {
    "runes": [
      "8230",
      "8226",
      "8210",
      "8236",
      "8473",
      "8451"
    ],
    "items": [
      "6657",
      "3040",
      "2522"
    ],
    "starters": [
      "1056",
      "2003",
      "3070"
    ],
    "boots": "3020",
    "fetchedAt": "2026-04-20T01:59:01.583Z"
  },
  "Ryze_top": {
    "runes": [
      "8230",
      "8226",
      "8210",
      "8236",
      "8473",
      "8451"
    ],
    "items": [
      "6657",
      "3040",
      "2522"
    ],
    "starters": [
      "1056",
      "2003",
      "3070"
    ],
    "boots": "3020",
    "fetchedAt": "2026-04-20T01:59:03.716Z"
  },
  "Azir_mid": {
    "runes": [
      "8008",
      "8009",
      "9104",
      "8017",
      "8226",
      "8236"
    ],
    "items": [
      "3115",
      "4645",
      "3157"
    ],
    "starters": [
      "1056",
      "2003"
    ],
    "boots": "3020",
    "fetchedAt": "2026-04-20T01:59:05.873Z"
  },
  "Anivia_mid": {
    "runes": [
      "8112",
      "8126",
      "8140",
      "8105",
      "8009",
      "8014"
    ],
    "items": [
      "6657",
      "3040",
      "6653"
    ],
    "starters": [
      "1056",
      "2003",
      "3070"
    ],
    "boots": "3009",
    "fetchedAt": "2026-04-20T01:59:07.823Z"
  },
  "Anivia_top": {
    "runes": [
      "8112",
      "8126",
      "8140",
      "8105",
      "8009",
      "8014"
    ],
    "items": [
      "6657",
      "3040",
      "6653"
    ],
    "starters": [
      "1056",
      "2003",
      "3070"
    ],
    "boots": "3009",
    "fetchedAt": "2026-04-20T01:59:10.264Z"
  },
  "Anivia_sup": {
    "runes": [
      "8112",
      "8126",
      "8140",
      "8105",
      "8009",
      "8014"
    ],
    "items": [
      "6657",
      "3040",
      "6653"
    ],
    "starters": [
      "1056",
      "2003",
      "3070"
    ],
    "boots": "3009",
    "fetchedAt": "2026-04-20T01:59:12.358Z"
  },
  "Swain_mid": {
    "runes": [
      "8010",
      "8009",
      "9105",
      "8299",
      "8429",
      "8451"
    ],
    "items": [
      "3116",
      "6653",
      "3157"
    ],
    "starters": [
      "2003"
    ],
    "boots": "3020",
    "fetchedAt": "2026-04-20T01:59:14.568Z"
  },
  "Swain_sup": {
    "runes": [
      "8010",
      "8009",
      "9105",
      "8299",
      "8429",
      "8451"
    ],
    "items": [
      "3116",
      "6653",
      "3157"
    ],
    "starters": [
      "2003"
    ],
    "boots": "3020",
    "fetchedAt": "2026-04-20T01:59:16.535Z"
  },
  "Swain_top": {
    "runes": [
      "8010",
      "8009",
      "9105",
      "8299",
      "8429",
      "8451"
    ],
    "items": [
      "3116",
      "6653",
      "3157"
    ],
    "starters": [
      "2003"
    ],
    "boots": "3020",
    "fetchedAt": "2026-04-20T01:59:18.647Z"
  },
  "Swain_adc": {
    "runes": [
      "8010",
      "8009",
      "9105",
      "8299",
      "8429",
      "8451"
    ],
    "items": [
      "3116",
      "6653",
      "3157"
    ],
    "starters": [
      "2003"
    ],
    "boots": "3020",
    "fetchedAt": "2026-04-20T01:59:20.739Z"
  },
  "Cassiopeia_mid": {
    "runes": [
      "8010",
      "8009",
      "9105",
      "8299",
      "8226",
      "8210"
    ],
    "items": [
      "6657",
      "3040",
      "3116"
    ],
    "starters": [
      "1056",
      "2003",
      "3070"
    ],
    "boots": null,
    "fetchedAt": "2026-04-20T01:59:22.729Z"
  },
  "Cassiopeia_top": {
    "runes": [
      "8010",
      "8009",
      "9105",
      "8299",
      "8226",
      "8210"
    ],
    "items": [
      "6657",
      "3040",
      "3116"
    ],
    "starters": [
      "1056",
      "2003",
      "3070"
    ],
    "boots": null,
    "fetchedAt": "2026-04-20T01:59:24.881Z"
  },
  "AurelionSol_mid": {
    "runes": [
      "8229",
      "8226",
      "8233",
      "8237",
      "8473",
      "8451"
    ],
    "items": [
      "2503",
      "3116",
      "6653"
    ],
    "starters": [
      "1056",
      "2003",
      "3070"
    ],
    "boots": "3020",
    "fetchedAt": "2026-04-20T01:59:26.856Z"
  },
  "Akshan_mid": {
    "runes": [
      "8005",
      "8009",
      "9104",
      "8014",
      "8473",
      "8451"
    ],
    "items": [
      "3087",
      "6676",
      "3031"
    ],
    "starters": [
      "1055",
      "2003",
      "1036",
      "2031"
    ],
    "boots": "3009",
    "fetchedAt": "2026-04-20T01:59:29.328Z"
  },
  "Akshan_top": {
    "runes": [
      "8005",
      "8009",
      "9104",
      "8014",
      "8473",
      "8451"
    ],
    "items": [
      "3087",
      "6676",
      "3031"
    ],
    "starters": [
      "1055",
      "2003",
      "1036",
      "2031"
    ],
    "boots": "3009",
    "fetchedAt": "2026-04-20T01:59:31.491Z"
  },
  "Elise_jg": {
    "runes": [
      "8128",
      "8126",
      "8140",
      "8105",
      "9111",
      "8014"
    ],
    "items": [
      "4646",
      "4645",
      "3157"
    ],
    "starters": [
      "1101",
      "2003"
    ],
    "boots": "3020",
    "fetchedAt": "2026-04-20T01:59:33.591Z"
  },
  "Elise_sup": {
    "runes": [
      "8128",
      "8126",
      "8140",
      "8105",
      "9111",
      "8014"
    ],
    "items": [
      "4646",
      "4645",
      "3157"
    ],
    "starters": [
      "1101",
      "2003"
    ],
    "boots": "3020",
    "fetchedAt": "2026-04-20T01:59:35.724Z"
  },
  "Ivern_jg": {
    "runes": [
      "8214",
      "8275",
      "8210",
      "8232",
      "8321",
      "8347"
    ],
    "items": [
      "3107",
      "6617",
      "3504"
    ],
    "starters": [
      "1102",
      "2003"
    ],
    "boots": "3020",
    "fetchedAt": "2026-04-20T01:59:37.717Z"
  },
  "Lillia_jg": {
    "runes": [
      "8010",
      "9111",
      "9105",
      "8014",
      "8304",
      "8347"
    ],
    "items": [
      "6653",
      "4633",
      "3157"
    ],
    "starters": [
      "1102",
      "2003"
    ],
    "boots": "3020",
    "fetchedAt": "2026-04-20T01:59:40.243Z"
  },
  "Lillia_top": {
    "runes": [
      "8010",
      "9111",
      "9105",
      "8014",
      "8304",
      "8347"
    ],
    "items": [
      "6653",
      "4633",
      "3157"
    ],
    "starters": [
      "1102",
      "2003"
    ],
    "boots": "3020",
    "fetchedAt": "2026-04-20T01:59:43.256Z"
  },
  "Viego_jg": {
    "runes": [
      "8010",
      "9111",
      "9104",
      "8014",
      "8304",
      "8347"
    ],
    "items": [
      "6672",
      "6676",
      "6673"
    ],
    "starters": [
      "1102",
      "2003"
    ],
    "boots": "3047",
    "fetchedAt": "2026-04-20T01:59:45.302Z"
  },
  "Viego_top": {
    "runes": [
      "8010",
      "9111",
      "9104",
      "8014",
      "8304",
      "8347"
    ],
    "items": [
      "6672",
      "6676",
      "6673"
    ],
    "starters": [
      "1102",
      "2003"
    ],
    "boots": "3047",
    "fetchedAt": "2026-04-20T01:59:47.342Z"
  },
  "Viego_mid": {
    "runes": [
      "8010",
      "9111",
      "9104",
      "8014",
      "8304",
      "8347"
    ],
    "items": [
      "6672",
      "6676",
      "6673"
    ],
    "starters": [
      "1102",
      "2003"
    ],
    "boots": "3047",
    "fetchedAt": "2026-04-20T01:59:50.277Z"
  },
  "Gwen_top": {
    "runes": [
      "8010",
      "8009",
      "9104",
      "8299",
      "8473",
      "8242"
    ],
    "items": [
      "2510",
      "4645",
      "3089"
    ],
    "starters": [
      "1056",
      "2003",
      "1054"
    ],
    "boots": "3020",
    "fetchedAt": "2026-04-20T01:59:54.209Z"
  },
  "Gwen_jg": {
    "runes": [
      "8010",
      "8009",
      "9104",
      "8299",
      "8473",
      "8242"
    ],
    "items": [
      "2510",
      "4645",
      "3089"
    ],
    "starters": [
      "1056",
      "2003",
      "1054"
    ],
    "boots": "3020",
    "fetchedAt": "2026-04-20T01:59:56.159Z"
  },
  "KSante_top": {
    "runes": [
      "8437",
      "8401",
      "8444",
      "8451",
      "8345",
      "8347"
    ],
    "items": [
      "6662",
      "2502",
      "6665"
    ],
    "starters": [
      "1054",
      "2003",
      "1029",
      "2031"
    ],
    "boots": "3047",
    "fetchedAt": "2026-04-20T01:59:58.169Z"
  },
  "Milio_sup": {
    "runes": [
      "8214",
      "8226",
      "8210",
      "8237",
      "8473",
      "8453"
    ],
    "items": [
      "6620",
      "6617",
      "3504"
    ],
    "starters": [
      "2003"
    ],
    "boots": "3009",
    "fetchedAt": "2026-04-20T02:00:01.026Z"
  },
  "Naafiri_mid": {
    "runes": [
      "8010",
      "9111",
      "9104",
      "8014",
      "8304",
      "8347"
    ],
    "items": [
      "6697",
      "6696",
      "6694"
    ],
    "starters": [
      "1101",
      "2003"
    ],
    "boots": "3047",
    "fetchedAt": "2026-04-20T02:00:03.183Z"
  },
  "Naafiri_jg": {
    "runes": [
      "8010",
      "9111",
      "9104",
      "8014",
      "8304",
      "8347"
    ],
    "items": [
      "6697",
      "6696",
      "6694"
    ],
    "starters": [
      "1101",
      "2003"
    ],
    "boots": "3047",
    "fetchedAt": "2026-04-20T02:00:05.388Z"
  },
  "Briar_jg": {
    "runes": [
      "8005",
      "9111",
      "9104",
      "8014",
      "8143",
      "8135"
    ],
    "items": [
      "3153",
      "3071",
      "6333"
    ],
    "starters": [
      "1102",
      "1101"
    ],
    "boots": "3047",
    "fetchedAt": "2026-04-20T02:00:07.375Z"
  },
  "Briar_top": {
    "runes": [
      "8005",
      "9111",
      "9104",
      "8014",
      "8143",
      "8135"
    ],
    "items": [
      "3153",
      "3071",
      "6333"
    ],
    "starters": [
      "1102",
      "1101"
    ],
    "boots": "3047",
    "fetchedAt": "2026-04-20T02:00:09.358Z"
  },
  "Hwei_mid": {
    "runes": [
      "8229",
      "8226",
      "8210",
      "8237",
      "9105",
      "8017"
    ],
    "items": [
      "2503",
      "6653",
      "4645"
    ],
    "starters": [
      "1056",
      "2003",
      "3070"
    ],
    "boots": "3020",
    "fetchedAt": "2026-04-20T02:00:15.079Z"
  },
  "Hwei_sup": {
    "runes": [
      "8229",
      "8226",
      "8210",
      "8237",
      "9105",
      "8017"
    ],
    "items": [
      "2503",
      "6653",
      "4645"
    ],
    "starters": [
      "1056",
      "2003",
      "3070"
    ],
    "boots": "3020",
    "fetchedAt": "2026-04-20T02:00:17.003Z"
  },
  "Smolder_adc": {
    "runes": [
      "8021",
      "8009",
      "9103",
      "8017",
      "8304",
      "8345"
    ],
    "items": [
      "3508",
      "3161",
      "3094"
    ],
    "starters": [
      "1055",
      "2003",
      "1056"
    ],
    "boots": "3009",
    "fetchedAt": "2026-04-20T02:00:19.133Z"
  },
  "Smolder_mid": {
    "runes": [
      "8021",
      "8009",
      "9103",
      "8017",
      "8304",
      "8345"
    ],
    "items": [
      "3508",
      "3161",
      "3094"
    ],
    "starters": [
      "1055",
      "2003",
      "1056"
    ],
    "boots": "3009",
    "fetchedAt": "2026-04-20T02:00:22.597Z"
  },
  "Ambessa_top": {
    "runes": [
      "8010",
      "9111",
      "9105",
      "8299",
      "8304",
      "8347"
    ],
    "items": [
      "6697",
      "6696",
      "6333"
    ],
    "starters": [
      "1101",
      "2003"
    ],
    "boots": "3047",
    "fetchedAt": "2026-04-20T02:00:25.114Z"
  },
  "Ambessa_jg": {
    "runes": [
      "8010",
      "9111",
      "9105",
      "8299",
      "8304",
      "8347"
    ],
    "items": [
      "6697",
      "6696",
      "6333"
    ],
    "starters": [
      "1101",
      "2003"
    ],
    "boots": "3047",
    "fetchedAt": "2026-04-20T02:00:27.098Z"
  },
  "Ambessa_mid": {
    "runes": [
      "8010",
      "9111",
      "9105",
      "8299",
      "8304",
      "8347"
    ],
    "items": [
      "6697",
      "6696",
      "6333"
    ],
    "starters": [
      "1101",
      "2003"
    ],
    "boots": "3047",
    "fetchedAt": "2026-04-20T02:00:29.032Z"
  },
  "Zaahen_top": {
    "runes": [
      "8010",
      "9111",
      "9105",
      "8014",
      "8473",
      "8453"
    ],
    "items": [
      "3078",
      "6610",
      "6333"
    ],
    "starters": [
      "1055",
      "2003",
      "1054"
    ],
    "boots": "3047",
    "fetchedAt": "2026-04-20T02:00:30.994Z"
  },
  "Zaahen_jg": {
    "runes": [
      "8010",
      "9111",
      "9105",
      "8014",
      "8473",
      "8453"
    ],
    "items": [
      "3078",
      "6610",
      "6333"
    ],
    "starters": [
      "1055",
      "2003",
      "1054"
    ],
    "boots": "3047",
    "fetchedAt": "2026-04-20T02:00:33.201Z"
  },
  "Aurora_mid": {
    "runes": [
      "8112",
      "8139",
      "8140",
      "8106",
      "8226",
      "8210"
    ],
    "items": [
      "3152",
      "4645",
      "3089"
    ],
    "starters": [
      "1056",
      "2003",
      "1082",
      "2031"
    ],
    "boots": "3020",
    "fetchedAt": "2026-04-20T02:00:35.364Z"
  },
  "Aurora_top": {
    "runes": [
      "8112",
      "8139",
      "8140",
      "8106",
      "8226",
      "8210"
    ],
    "items": [
      "3152",
      "4645",
      "3089"
    ],
    "starters": [
      "1056",
      "2003",
      "1082",
      "2031"
    ],
    "boots": "3020",
    "fetchedAt": "2026-04-20T02:00:37.685Z"
  },
  "Yunara_adc": {
    "runes": [
      "8008",
      "9111",
      "9103",
      "8017",
      "8321",
      "8313"
    ],
    "items": [
      "6672",
      "2512",
      "3031"
    ],
    "starters": [
      "1055",
      "2003"
    ],
    "boots": "3006",
    "fetchedAt": "2026-04-20T02:00:39.687Z"
  },
  "Heimerdinger_top": {
    "runes": [
      "8010",
      "8009",
      "9105",
      "8017",
      "8233",
      "8236"
    ],
    "items": [
      "2503",
      "6653",
      "3157"
    ],
    "starters": [
      "1056",
      "2003",
      "1082",
      "2031"
    ],
    "boots": "3020",
    "fetchedAt": "2026-04-20T02:00:41.632Z"
  },
  "Heimerdinger_mid": {
    "runes": [
      "8010",
      "8009",
      "9105",
      "8017",
      "8233",
      "8236"
    ],
    "items": [
      "2503",
      "6653",
      "3157"
    ],
    "starters": [
      "1056",
      "2003",
      "1082",
      "2031"
    ],
    "boots": "3020",
    "fetchedAt": "2026-04-20T02:00:43.803Z"
  },
  "Heimerdinger_sup": {
    "runes": [
      "8010",
      "8009",
      "9105",
      "8017",
      "8233",
      "8236"
    ],
    "items": [
      "2503",
      "6653",
      "3157"
    ],
    "starters": [
      "1056",
      "2003",
      "1082",
      "2031"
    ],
    "boots": "3020",
    "fetchedAt": "2026-04-20T02:00:46.753Z"
  },
  "Rammus_jg": {
    "runes": [
      "8439",
      "8463",
      "8429",
      "8242",
      "9111",
      "9104"
    ],
    "items": [
      "3075",
      "3068",
      "6665"
    ],
    "starters": [
      "1102",
      "2003"
    ],
    "boots": "3047",
    "fetchedAt": "2026-04-20T02:00:49.164Z"
  },
  "Belveth_jg": {
    "runes": [
      "8010",
      "9111",
      "9104",
      "8014",
      "8304",
      "8347"
    ],
    "items": [
      "6672",
      "6631",
      "6333"
    ],
    "starters": [
      "1102",
      "2003"
    ],
    "boots": "3047",
    "fetchedAt": "2026-04-20T02:00:51.144Z"
  },
  "Karthus_jg": {
    "runes": [
      "8128",
      "8126",
      "8140",
      "8135",
      "8009",
      "8014"
    ],
    "items": [
      "2503",
      "4645",
      "3089"
    ],
    "starters": [
      "1101",
      "2003"
    ],
    "boots": "3020",
    "fetchedAt": "2026-04-20T02:00:54.310Z"
  },
  "Karthus_mid": {
    "runes": [
      "8128",
      "8126",
      "8140",
      "8135",
      "8009",
      "8014"
    ],
    "items": [
      "2503",
      "4645",
      "3089"
    ],
    "starters": [
      "1101",
      "2003"
    ],
    "boots": "3020",
    "fetchedAt": "2026-04-20T02:00:56.260Z"
  },
  "Maokai_jg": {
    "runes": [
      "8439",
      "8463",
      "8473",
      "8242",
      "8345",
      "8347"
    ],
    "items": [
      "3002",
      "2524",
      "3190"
    ],
    "starters": [
      "2003"
    ],
    "boots": "3009",
    "fetchedAt": "2026-04-20T02:00:58.298Z"
  },
  "Maokai_sup": {
    "runes": [
      "8439",
      "8463",
      "8473",
      "8242",
      "8345",
      "8347"
    ],
    "items": [
      "3002",
      "2524",
      "3190"
    ],
    "starters": [
      "2003"
    ],
    "boots": "3009",
    "fetchedAt": "2026-04-20T02:01:00.298Z"
  },
  "Maokai_top": {
    "runes": [
      "8439",
      "8463",
      "8473",
      "8242",
      "8345",
      "8347"
    ],
    "items": [
      "3002",
      "2524",
      "3190"
    ],
    "starters": [
      "2003"
    ],
    "boots": "3009",
    "fetchedAt": "2026-04-20T02:01:02.281Z"
  },
  "Vex_mid": {
    "runes": [
      "8112",
      "8139",
      "8140",
      "8106",
      "8226",
      "8210"
    ],
    "items": [
      "6655",
      "4645",
      "3157"
    ],
    "starters": [
      "1056",
      "2003",
      "1082",
      "2031"
    ],
    "boots": "3020",
    "fetchedAt": "2026-04-20T02:01:04.402Z"
  },
  "LeBlanc_mid": {
    "runes": [
      "8112",
      "8143",
      "8140",
      "8105",
      "8210",
      "8236"
    ],
    "items": [
      "6655",
      "4645",
      "3089"
    ],
    "starters": [
      "1056",
      "2003",
      "1082",
      "2031"
    ],
    "boots": "3020",
    "fetchedAt": "2026-04-20T02:01:06.583Z"
  },
  "LeBlanc_sup": {
    "runes": [
      "8112",
      "8143",
      "8140",
      "8105",
      "8210",
      "8236"
    ],
    "items": [
      "6655",
      "4645",
      "3089"
    ],
    "starters": [
      "1056",
      "2003",
      "1082",
      "2031"
    ],
    "boots": "3020",
    "fetchedAt": "2026-04-20T02:01:08.518Z"
  },
  "Rell_sup": {
    "runes": [
      "8439",
      "8401",
      "8473",
      "8242",
      "8306",
      "8347"
    ],
    "items": [
      "3050",
      "3190",
      "3109"
    ],
    "starters": [
      "2003"
    ],
    "boots": "3047",
    "fetchedAt": "2026-04-20T02:01:10.528Z"
  },
  "Neeko_sup": {
    "runes": [
      "8229",
      "8226",
      "8210",
      "8237",
      "8345",
      "8347"
    ],
    "items": [
      "3152",
      "3157",
      "3165"
    ],
    "starters": [
      "2003"
    ],
    "boots": "3020",
    "fetchedAt": "2026-04-20T02:01:12.612Z"
  },
  "Neeko_mid": {
    "runes": [
      "8229",
      "8226",
      "8210",
      "8237",
      "8345",
      "8347"
    ],
    "items": [
      "3152",
      "3157",
      "3165"
    ],
    "starters": [
      "2003"
    ],
    "boots": "3020",
    "fetchedAt": "2026-04-20T02:01:14.763Z"
  }
}